Workbook
Name _Hlk139297106: Правило!$C$29
Name _Hlk139297106: Протокол!$C$29

Sheet Протокол
I3: Общество с ограниченной ответственностью «А-Профит»
I4: (ООО «А-Профит»)
I5: Адрес места нахождения юридического лица:
I6: 690074, Россия, Приморский край, г. Владивосток, ул. Снеговая, д. 64, офис 1
I7: Тел.: 89240037850, e-mail: a_profit_lab@mail.ru
I9: Испытательная лаборатория ООО «А-Профит»
I10: (ООО «А-Профит»)
I11: Адреса мест осуществления деятельности:
I12: 690074, Россия, Приморский край, г. Владивосток, ул. Снеговая, д. 64
I13: Тел.: 89240037850, e-mail: a_profit_lab@mail.ru
M16: УТВЕРЖДАЮ
M18: Руководитель ИЛ ООО «А-Профит»
O19: А.Г. Луговой
M20: Подпись | O20: И.О. Фамилия
M21: =L28 -> 46132
I22: М.П.
G28: Протокол № | I28: РАБ01 | K28: от | L28: 46132 | N28: г.
C29: идентификации, технической экспертизы конструкции, исследований, испытаний и измерений транспортного средства на соответствия предъявляемым требованиям ТР ТС 018/2011 к Единичным транспортным средствам
H73: Результаты исследований, испытаний и измерений относятся только к образцу (объекту), предоставленному заказчиком.
H74: Результаты исследований, испытаний и измерений относятся только к образцу (объекту), прошедшему исследования,
H75: испытания и измерения в испытательной лаборатории ООО «А-Профит».
H76: Протокол не может быть частично воспроизведен без письменного разрешения лаборатории.
H77: Испытательная лаборатория (центр) несет ответственность за всю информацию, предоставленную в протоколе
H78: испытаний, за исключением случаев, когда информация предоставлена заказчиком.
A80: Протокол идентификации, технической экспертизы конструкции, исследований, испытаний и измерений транспортного средства на соответствия предъявляемым требованиям
E81: ТР ТС 018/2011 к Единичным транспортным средствам № | J81: =I28 -> РАБ01 | L81: от | M81: =L28 -> 46132
I83: 1. ОБЪЕКТ ИСПЫТАНИЙ
B84: Таблица 1.1 Общие сведения
A85: Наименование образца испытаний (идентификация объекта, поступившего на испытания: марка, тип/обозначение, заводской номер, другая уникальная идентифицирующая информация) | F85: Транспортное средство:
F86: Марка | K86: Kia
F87: коммерческое название | K87: Rio
F88: тип | K88: CB41
F89: Индефикационный номер (VIN) или серийный (заводской) номер | K89: Z94CB41BBHR378731
F90: Гос. Номер | K90: С360СС 25RUS
F91: Категория | K91: М1
A92: Наименование и контактные данные заказчика* (для юридических лиц указывают наименование, юридический адрес и фактический адрес места осуществления деятельности; для ИП указывают инициалы, фамилию, адрес регистрации; для физического лица указывают инициалы, фамилию, почтовый адрес) | F92: ООО «А-Профит» Адрес места нахождения юридического лица: 690074, Россия, Приморский край, г. Владивосток, ул. Снеговая, д. 64, офис 1 Адреса мест осуществления деятельности: 690074, Россия, Приморский край, г. Владивосток, ул. Снеговая, д. 64
A97: Наименование и адрес изготовителя (юридический адрес и фактический адрес места осуществления деятельности) | F97: Изготовитель: ООО "Хендэ Мотор Мануфактуринг Рус" Адрес юридический и фактический: 197701, г. Санкт-Петербург, Курортный район, г. Сестрорецк, Левашовское шоссе, д.20, лит А, Российская Федерация Сборочный завод: ООО "Хендэ Мотор Мануфактуринг Рус" Адрес юридический и фактический: 197701, г. Санкт-Петербург, Курортный район, г. Сестрорецк, Левашовское шоссе, д.20, лит А, Российская Федерация
A100: Данные об отборе образца | F100: Образец предоставлен заказчиком, ИЛ не несет ответственности за данные отбора образца
A102: Дата получения образца | F102: =L28 -> 46132
A103: Дата(ы) начала и окончания испытаний | F103: =L28 -> 46132
A104: Цель осуществления проведения испытаний | F104: Оценка соответствия определяемых в рамках испытаний характеристик единичного транспортного средства требованиям TP TC 018/2011
A106: Идентификация применяемого метода | F106: ГОСТ 33670-2015, приложение А п. А.1.1, п. А.1.2, п. А.1.2.1, п. А.1.2.2, п. А.1.2.3, п. А.1.2.4, п. А.2.1, п. А.3.1, п. А.3.2, п. А.5.1.1.1, п. А.5.1.1.2, п. А.5.1.1.3, п. А.5.1.1.4, п. А.5.1.2.1, п. А.5.1.2.2, п. А.5.1.3.1, п. А.5.1.3.2, п. А.5.1.4, п. А.5.1.4.1- 5.1.4.2, п. А.5.1.4.3, п. А.5.1.5, п. А.5.2, п. А.5.3, п. А.5.4, п. А.5.5.1.1, п. А.5.5.1.1.1, п. А.5.5.1.1.2, п. А.5.5.1.2, п. А.5.5.1.3, п. А.5.5.2.1, п. А.5.5.2.2, п. А.5.7, п. А.5.8, п. А.5.9, п. А.5.11.1, п. А.5.11.2, п. А.5.11.3, п. А.5.11.4, п. А.5.11.5, п. А.5.11.6, п. А.5.11.7, п. А.5.11.8, п. А.5.12, п. А.5.13, п. А.5.15.1, п. А.5.15.2, п. А.5.16, п. А.6.1, п. А.6.2, п. А.6.3, п. А.6.4, п. А.6.5, п. А.6.6, п. А.6.7, п. А.6.8, п. А.6.9, п. А.7.1, п. А.7.2, п. А.7.3, п. А.7.4, п. А.7.5, п. А.7.6, п. А.7.7, п. А.8.1, п. А.8.2, п. А.8.3, п. А.8.4, п. А.8.5, п. А.8.6, п. А.8.7, п. А.8.8, п. А.8.9, п. А.8.10.1, п. А.8.10.2, п. А.8.10.3, п. А.8.11, п. А.8.12.1, п. А.8.12.2, п. А.8.12.3, п. А.8.12.4, п. А.8.13.1, п. А.8.13.2, п. А.8.14, п. А.8.15, п. А.8.16, п. А.8.17, п. А.8.18, п. А.8.18.2, п. А.8.18.3, п. А.8.18.4, п. А.8.19, п. А.8.20.1, п. А.8.20.2, п. А.8.20.3, п. А.8.20.4, п. А.8.20.5, п. А.8.20.6, п. А.8.20.7, п. А.8.20.8, п. А.8.21, п. А.8.22.1, п. А.8.22.2, п. А.8.22.3, п. А.8.23.1, п. А.8.23.2, п. А.8.24.1, п. А.8.24.2, п. А.8.24.3, п. А.8.25, п. А.8.26, п. А.8.27, п. А.8.28, п. А.10.1, п. А.10.2, п. А.10.3, п. А.10.4 п. А.10.5, п. А.10.6, п. А.10.7.1, п. А.10.7.2, п. А.10.7.3, п. А.10.7.4, п. А.10.7.5, п. А.10.8.1, п. А.10.8.2, п. А.10.8.3, п. А.10.8.4, п. А.10.9.1, п. А.10.9.2, п. А.10.9.2.1, п. А.10.9.2.2, п. А.10.9.2.3, п. А.10.9.2.4, п. А.10.9.2.5, п. А.10.9.3, А.11.1, п. А.11.2, п. А.11.3, п. А.11.4 п. А.11.5, п. А.11.6, п. А.11.8, п. А.11.9, п. А.11.10, п. А.11.11, п. А.11.12 п. А.11.13, п. А.11.14, п. А.11.15, п. А.11.16, п. А.11.17, п. А.12.1, п. А.12.2, п. А.12.3, п. А.13.1, п. А.13.2, п. А.13.3.1, п. А.13.3.2, п. А.13.4, п. А.13.5, п. А.13.6, п. А.13.7.1, п. А.13.7.2, п. А.13.8, п. А.13.9, п. А.13.10, п. А.13.11, п. А.13.12, п. А.13.13, п. А.13.14, п. А.13.15, п. А.13.16, п. А.13.17, п. А.13.19.1, п. А.13.19.2, п. А.13.19.3, п. А.13.19.4, п. А.13.20, п. А.13.21, п. А.14.1, п. А.14.2, п. А.14.3, п. А.15.1, п. А.15.2, п. А.15.3, п. А.16.1, п. А.16.2, п. А.16.3, п. А.16.4, п. А.16.5, п. А.16.6, п. А.16.7, п. А.16.8, п. А.16.9, п. А.16.11, п. А.16.12, п. А.16.13, п. А.16.14, п. А.16.15, п. А.16.16, п. А.16.17, п. А.16.18, п. А.17.1, п. А.17.2, п. А.17.3, п. А.18.1, п. А.18.2, п. А.18.3, п. А.18.4, п. А.18.4.1, п. А.18.4.2, п. А.18.4.3, п. А.18.4.4, п. А.18.5, п. А.20.1, п. А.20.2, п. А.20.3, п. А.20.5, п. А.20.5.1, п. А.20.5.2, п. А.20.5.3, п. А.20.6, п. А.20.7, п. А.20.8, п. А.21.1, п. А.21.2, п. А.21.3, п. А.21.4, п. А.21.5, п. А.21.6, п. А.21.7, п. А.21.8, п. А.21.9, п. А.22.1, п. А.22.2, п. А.22.3, п. А.22.4, п. А.22.5.1, п. А.22.5.2, п. А.22.5.3, п. А.22.5.4, п. А.22.5.5, п. А.22.5.6.1, п. А.22.5.6.2, п. А.22.5.6.3, п. А.23.1, п. А.23.2, п. А.24.1, п. А.24.2, п. А.24.3, п. А.24.4, п. А.24.5, п. А.24.6, п. А.26.1, п. А.26.2, п. А.26.3, п. А.26.4, п. А.26.5, п. А.26.6, п. А.26.7, п. А.26.8, п. А.26.9, п. А.26.10, п. А.26.11, п. А.26.12, п. А.26.13, п. А.26.14, п. А.26.15, п. А.26.16, п. А.26.17, п. А.27.1, п. А.27.2, п. А.27.3, п. А.27.4, п. А.27.5 Приложение В, Приложение Г, ГОСТ 33997-2016 п. 5.11.14, СТБ 914-99 Приложение Е, п.Е.4.7, ГОСТ 22748-77, п. 2.2.1, п. 2.2.5, п. 2.2.21, п. 2.2.27, ГОСТ 33987-2016, Приложение В, Приложение Г
A129: Место (места) осуществления испытаний (адрес места проведения испытаний) | F129: 690074, Россия, Приморский край, г. Владивосток, ул. Снеговая, д. 64
B131: * Информация предоставлена заказчиком, который несет полную ответственность за эти данные
I133: 2. УСЛОВИЯ ПРОВЕДЕНИЯ ИСПЫТАНИЙ
B134: Таблица 2.1 Описание условий окружающей среды и параметров электрической сети
A135: Наименование показателя | F135: Значение (при проведении испытаний)
A136: Условия проведения испытаний
A137: Температура окружающей среды | F137: 20 | M137: °С
A138: Относительная влажность | F138: 50 | M138: %
A139: Атмосферное давление | F139: 99.5 | M139: кПа
A140: Условия проведения испытаний в дорожных условиях
A141: Температура окружающей среды | F141: =F137 -> 20 | M141: =M137 -> °С
A142: Относительная влажность | F142: =F138 -> 50 | M142: =M138 -> %
A143: Атмосферное давление | F143: - | M143: =M139 -> кПа
A144: Параметры электрической сети
A145: Частота электрической сети, Гц | F145: 50 | M145: Гц
A146: Напряжение в сети, В | F146: Фаза а-ноль | K146: Фаза b-ноль | O146: Фаза c-ноль
F147: 213 | I147: В | K147: 219 | M147: В | O147: 216 | Q147: В
F148: Фаза b-фаза c | K148: Фаза b-фаза c | O148: Фаза a-фаза c
F149: 375 | I149: В | K149: 377 | M149: В | O149: 371 | Q149: В
B150: Таблица 2.2 Проверка выполнения требований к единичным ТС
A151: Требования | F151: Отметка о соответствии/несоответствии
A152: Соответствие требованиям п. 3.1. ГОСТа 33670-2015 | F152: соответствует
A153: Соответствие требованиям п. 3.2. ГОСТа 33670-2015 | F153: соответствует
A154: Соответствие требованиям п. 3.3. ГОСТа 33670-2015 | F154: соответствует
A156: Протокол идентификации, технической экспертизы конструкции, исследований, испытаний и измерений транспортного средства на соответствия предъявляемым требованиям
E157: ТР ТС 018/2011 к Единичным транспортным средствам № | J157: =J81 -> РАБ01 | L157: от | M157: =M81 -> 46132
H159: 3. СВЕДЕНИЯ О ПРИМЕНЯЕМОМ ОБОРУДОВАНИИ
A160: Средства измерения
A161: № п/п | B161: Наименование испытательного оборудования, средств измерения | D161: Диапазон измерений | F161: Класс точности (разряд), погрешность | M161: Сведения о результатах поверки СИ (номер, дата, срок действия) | Q161: Заводской или инвентарный номер
A162: 1 | B162: Измеритель параметров света фар автотранспортных средств ИПФ-01 | D162: от 0 до 2° 20’ (угол наклона) от 200 до 125000 кД (сила света) от 1 до 2Гц (частота проблесков) | F162: Абсолютная погрешность измерения углов наклона светотеневой границы светового пучка фары в вертикальной плоскости: ±0,1% Абсолютная погрешность установки оптической камеры измерителя в горизонтальной плоскости: ±30' Относительная погрешность измерения силы света внешних световых источников: ±15% Абсолютная погрешность измерения частоты следования световых проблесков фонарей указателей поворота: ±0,1 Гц | M162: =Оборудование!M5 -> Св-во № С-АЭ/06-08-2025/ 453157456 от | Q162: № СИ001
M163: =Оборудование!M6 -> 45875 | O163: =Оборудование!O6 -> г., 12 мес.
A164: 2 | B164: Преобразователь измерительный угла поворота ИСЛ-М | D164: от 0 до 50° | F164: Максимальная погрешность измерения суммарного люфта: ±0,5° | M164: =Оборудование!M7 -> Св-во № С-АЭ/02-06-2025/ 436547222 от | Q164: № СИ002
M165: =Оборудование!M8 -> 45810 | O165: =Оборудование!O8 -> г., 12 мес.
A166: 3 | B166: Дымомер АВГ-1Д-4.01 | D166: от 0,00 до ∞ от 0,0 до 100,0% от 0 до 6000 мин 0 до +100°С | F166: абсолютная погрешность при коэффициенте поглощения 1,6-1,8м-1: ±0,05 Погрешность: ±1,0 % Погрешность: ±2,5 % Погрешность: ±2,5 % | M166: =Оборудование!M9 -> Св-во № С-АЭ/02-06-2025/ 436579464 от | Q166: № СИ003
M167: =Оборудование!M10 -> 45810 | O167: =Оборудование!O10 -> г., 12 мес.
A168: 4 | B168: Измеритель светопропускания стекол "ТОНИК" | D168: от 4 до 100% | F168: Абсолютная погрешность ±2,0% | M168: =Оборудование!M11 -> Св-во № С-АЭ/06-08-2025/ 453155401 от | Q168: № СИ004
M169: =Оборудование!M12 -> 45875 | O169: =Оборудование!O12 -> г., 12 мес.
A170: 5 | B170: Газоанализатор многокомпонентный «Автотест-02.02» 0 кл | D170: Углеводороды от 0 до 2000 млн1 оксид углерода от 0 до 5%, диоксид углерода от 0 до 16%, кислород от 0 до 21%, окислы азота от 0 до 5000 млн1 λ-параметр 0,5-2,00 частота оборотов от 0-8000 мин1 температура масла от 0 до 125°С | F170: Абсолютная погрешность: ±10млн1, относительная погрешность: ±5% Абсолютная погрешность: ±0,03%, относительная погрешность: ±3% Абсолютная погрешность: ±0,5%, относительная погрешность: ±4% Абсолютная погрешность: ±0,1%, относительная погрешность: ±3% Абсолютная погрешность: ±50млн1, относительная погрешность: ±5% Не нормируется Относительная погрешность: ±2,5% Абсолютная погрешность: ±2°С | M170: =Оборудование!M13 -> Св-во № С-АЭ/10-07-2025/ 446406612 от | Q170: № СИ005
M171: =Оборудование!M14 -> 45848 | O171: =Оборудование!O14 -> г., 12 мес.
A172: 6 | B172: Стенд тормозной СТН 13000.01 | D172: от 0 до 30 кН (тормозная сила) от 0 до 1000Н (сила на органе управления) от 0 до 13000кг (масса ТС) | F172: Относительная погрешность: ±3% (тормозная сила) ±5% (сила на органе управления) ±3% (масса ТС) | M172: =Оборудование!M15 -> Св-во№ С-АЭ/05-09-2025/ 461489585 от | Q172: № СИ006
M173: =Оборудование!M16 -> 45905 | O173: =Оборудование!O16 -> г., 12 мес.
A174: 7 | B174: Рулетка измерительная металлическая Р30У2К | D174: от 0 до 30м | F174: Класс 2 Допускаемое отклонение: мм±0,15, см±0,20, дц±0,30, м ±[0,30+0,15(L-l)] | M174: =Оборудование!M17 -> Св-во № С-АЭ/05-09-2025/ 461447340 от | Q174: № СИ007
M175: =Оборудование!M18 -> 45905 | O175: =Оборудование!O18 -> г., 12 мес.
A176: 8 | B176: Штангенциркуль ШЦ-I-150 0,05 | D176: от 0 до 100мм | F176: Погрешность показаний: ±0,05мм | M176: =Оборудование!M19 -> Св-во № С-АЭ/02-06-2025/ 436547220 от | Q176: № СИ008
M177: =Оборудование!M20 -> 45810 | O177: =Оборудование!O20 -> г., 12 мес.
A178: 9 | B178: Угломер маятниковый ЗУРИ-М | D178: от 0 до 360° | F178: Погрешность показаний: ±1º | M178: =Оборудование!M21 -> Св-во № С-АЭ/21-08-2025/ 458005858 от | Q178: № СИ009
M179: =Оборудование!M22 -> 45890 | O179: =Оборудование!O22 -> г., 12 мес.
A180: 10 | B180: Прибор комбинированный Testo 622 | D180: от-10 до +60 °С от 10 до 95 % от 30 до 120 кПа | F180: Погрешность: ±0,4 °С ±3 % ±0,5 кПа | M180: =Оборудование!M23 -> Св-во № С-ВЦЛ/01-09-2025/ 460740052 от | Q180: № СИ010
M181: =Оборудование!M24 -> 45901 | O181: =Оборудование!O24 -> г., 12 мес.
A182: 11 | B182: Термометр инфракрасный Testo 830-Т 1 | D182: от -30°C до +400°C | F182: Погрешность показаний: ±1,5°C (от +0,1 до +400°C) ±2,0°C (от -30 до 0°C) | M182: =Оборудование!M25 -> Св-во № С-АЭ/19-08-2025/ 457455641 от | Q182: № СИ011
M183: =Оборудование!M26 -> 45888 | O183: =Оборудование!O26 -> г., 12 мес.
A184: 12 | B184: Измеритель скорости и длины ИСД-5.1 | D184: от 0,5 км/ч до 180 км/ч | F184: Пределы допускаемой относительной среднеквадратичной погрешности измерения скорости ±0,15% и длины ±0,1% - на длине не менее 20 м | M184: =Оборудование!M27 -> Св-во № С-С/15-10-2025/474327055 от | Q184: № СИ013
M185: =Оборудование!M28 -> 45945 | O185: =Оборудование!O28 -> г., 12 мес.
A186: 13 | B186: Шумомер-анализатор спектра портативный ОКТАВА-111 + микрофонный предусилитель Р200 | D186: от 19дБА до 141дБА | F186: Класс 1 Погрешность показаний: ±0,5 дБА | M186: =Оборудование!M29 -> Св-во № С-АЭ/19-08-2025/ 457406029 от | Q186: № СИ014
M187: =Оборудование!M30 -> 45888 | O187: =Оборудование!O30 -> г., 12 мес.
A188: 14 | B188: Калибратор акустический AK-1000 | D188: 1000 Гц в режиме основного тона, 94,0 и 114,0 дБ относительно 20 мкПа 114,0 Основной уровень | F188: Класс 1 Погрешность показаний: ±0,5 дБ Предел допускаемой абсолютной погрешности при нормальных условиях ±0,25 дБ Предел допускаемой дополнительной погрешности, вызванной изменением температуры ±0,08 дБ Пределы отклонения уровня звукового давления при изменениях напряжения электропитания ±0,07дБ | M188: =Оборудование!M31 -> Св-во № С-АЭ/08-09-2025/ 461980384 от | Q188: № СИ015
M189: =Оборудование!M32 -> 45908 | O189: =Оборудование!O32 -> г., 12 мес.
A190: 15 | B190: Динамометр электронный АЦД/1У-0,5/1И-1 | D190: от 0,05кН до 0,5кН | F190: Погрешность показаний ±0,24% | M190: =Оборудование!M33 -> С-во № С-АЭ/21-08-2025/ 458005861 от | Q190: № СИ016
...

Sheet Расчет
B1: 1. Расчет неопределенности измерений угла наклона государственного регистрационного знака и высоты от опорной плоскости верхнего края государственного регистрационного знака
B3: Используемое оборудование
B4: Заводской № | D4: Модель | G4: Ед. изм. | H4: Пределы допускаемой абсолютной погрешности | K4: Примечание
B5: 9405 | D5: Угломер маятниковый З УРИ-М | G5: градус | H5: ± | I5: 1
B6: 4-24020385 | D6: Угломер с нониусом Micron, мождификация УНЛ-360 | G6: минута | H6: ± | I6: 5
G7: мм | H7: ± | I7: 0.15 | K7: Миллимитровый интервал
B8: 2438 | D8: Рулетка RGK R-5 | G8: мм | H8: ± | I8: 0.2 | K8: сантимитровый интервал
G9: мм | H9: ± | I9: 0.3 | K9: дециметровый интервал
G10: мм | H10: ± | I10: (0,30+0,15(L-1)) | K10: отрезок шкалы 1 м и более
B11: Результаты измерений
B12: Угол между плоскостью государственного регистрационного знака и продольной плоскостью симметрии ТС, град | H12: Передний | I12: Задний
H13: =Вводные!H2 -> 90 | I13: =Вводные!I2 -> 90
B14: Угол между плоскостью государственного регистрационного знака и опорной поверхностью, град | H14: Передний | I14: Задний
H15: =Вводные!H4 -> 90 | I15: =Вводные!I4 -> 90
B16: Высота от опорной плоскости верхнего края государственного регистрационного знака, мм | H16: Передний | I16: Задний
H17: =Вводные!H6 -> 302 | I17: =Вводные!I6 -> 600
B18: Высота от опорной плоскости нижнего края государственного регистрационного знака, мм | H18: Передний | I18: Задний
H19: =Вводные!H8 -> 500 | I19: =Вводные!I8 -> 500
B20: 1.1. Расчет неопределенности измерений угла между плоскостью государственного регистрационного знака и продольной плоскостью симметрии ТС
B21: Суммарная стандартная неопределенность измерения угла между плоскостью государственного регистрационного знака и продольной плоскостью симметрии ТС:
E22: формула 10 ГОСТ 34100.3-2017/ISO/IEC Guide 98-3:2008
B24: где | D24: стандартная неопределенность измерения угла между плоскостью государственного регистрационного знака и продольной плоскостью симметрии ТС, оцененная по типу А
D25: стандартная неопределенность измерения угла между плоскостью государственного регистрационного знака и продольной плоскостью симметрии ТС, оцененная по типу B
B27: Стандартная неопределенность измерения угла между плоскостью государственного регистрационного знака и продольной плоскостью симметрии ТС, оцененная по типу B
D28: где | E28: = | F28: =I6/60 -> 0.083333333 | G28: ˚ | H28: абсолютная погрешность угломера с нониусом 4УМ
C30: = | D30: =F28/(3^0.5) -> 0.048112522 | E30: ˚
B32: Бюджет неопределенности
B33: Формула для расчета определяемой величины:
B34: где | D34: результат измерения угла между плоскостью государственного регистрационного знака и продольной плоскостью симметрии ТС
D35: поправка на погрешность средства измерений
B36: Бюджет неопределенности для измерения угла между плоскостью переднего государственного регистрационного знака и продольной плоскостью симметрии ТС
B37: Входная величина | D37: Оценка входной величины, градусы | F37: Стандартная неопределенность, градусы | H37: Распределение | J37: Коэффициент чувствительности | L37: Вклад в неопределенность | N37: Процент вклада, %
D38: =H13 -> 90 | F38: 0 | H38: нормальное | J38: 1 | L38: 0 | N38: 0
D39: 0 | F39: =D30 -> 0.048112522 | H39: прямоугольное | J39: 1 | L39: =F39 -> 0.048112522 | N39: 100
D40: =D38 -> 90 | F40: =F39 -> 0.048112522 | N40: 100
B42: Бюджет неопределенности для измерения угла между плоскостью заднего государственного регистрационного знака и продольной плоскостью симметрии ТС
B43: Входная величина | D43: Оценка входной величины, градусы | F43: Стандартная неопределенность, градусы | H43: Распределение | J43: Коэффициент чувствительности | L43: Вклад в неопределенность | N43: Процент вклада, %
D44: =I13 -> 90 | F44: 0 | H44: нормальное | J44: 1 | L44: 0 | N44: 0
D45: 0 | F45: =D30 -> 0.048112522 | H45: прямоугольное | J45: 1 | L45: =F45 -> 0.048112522 | N45: 100
D46: =D44 -> 90 | F46: =F45 -> 0.048112522 | N46: 100
B48: Расширенная неопределенность U получается умножением суммарной стандартной неопределенности на коэффициент охвата k, который выбирается равным 1,65 при уровне доверия 95 % в предположении прямоугольного распределения вероятностей измеряемой величины:
F50: k= | G50: 1.65
B52: U= | C52: =G50*D30 -> 0.079385662 | D52: ˚
B54: Представление результата измерения
B55: Угол между плоскостью переднего государственного регистрационного знака и продольной плоскостью симметрии, при , k = 1,65, Р = 95%: | O55: =D40 -> 90 | P55: =H6 -> ± | Q55: =C52 -> 0.079385662 | R55: ˚
B56: Угол между плоскостью заднего государственного регистрационного знака и продольной плоскостью симметрии при , k = 1,65, Р = 95%: | O56: =D46 -> 90 | P56: =P55 -> ± | Q56: =C52 -> 0.079385662 | R56: ˚
B58: 1.2. Расчет неопределенности измерений угла между плоскостью государственного регистрационного знака и опорной поверхностью
B59: Суммарная стандартная неопределенность измерения угла между плоскостью государственного регистрационного знака и опорной поверхностью:
F61: формула 10 ГОСТ 34100.3-2017/ISO/IEC Guide 98-3:2008
B63: где | F63: стандартная неопределенность измерения угла между плоскостью государственного регистрационного знака и опорной поверхностью, оцененная по типу А
F64: стандартная неопределенность измерения угла между плоскостью государственного регистра-ционного знака и опорной поверхностью, оцененная по типу B
B66: Стандартная неопределенность измерения угла между плоскостью государственного регистрационного знака и опорной поверхностью, оцененная по типу B
C68: = | D68: =I5/(3^0.5) -> 0.57735027 | E68: ˚
B70: где | C70: = | D70: =I5 -> 1 | E70: ˚ | F70: абсолютная погрешность угломера маятникового З УРИ-М
B72: Бюджет неопределенности.
B73: Формула для расчета определяемой величины:
B74: где | D74: результат измерения угла между плоскостью государственного регистрационного знака и опор-ной поверхностью
D75: поправка на погрешность средства измерений
B77: Бюджет неопределенности для измерения угла между плоскостью переднего государственного регистрационного знака и опорной поверхностью
B78: Входная величина | D78: Оценка входной величины, градусы | F78: Стандартная неопределенность, градусы | H78: Распределение | J78: Коэффициент чувствительности | L78: Вклад в неопределенность | N78: Процент вклада, %
D79: =H15 -> 90 | F79: 0 | H79: нормальное | J79: 1 | L79: 0 | N79: 0
D80: 0 | F80: =D68 -> 0.57735027 | H80: прямоугольное | J80: 1 | L80: =F80 -> 0.57735027 | N80: 100
D81: =D79 -> 90 | F81: =F80 -> 0.57735027 | N81: 100
B83: Бюджет неопределенности для измерения угла между плоскостью заднего государственного регистрационного знака и опорной поверхностью
B84: Входная величина | D84: Оценка входной величины, градусы | F84: Стандартная неопределенность, градусы | H84: Распределение | J84: Коэффициент чувствительности | L84: Вклад в неопределенность | N84: Процент вклада, %
D85: =I15 -> 90 | F85: 0 | H85: нормальное | J85: 1 | L85: 0 | N85: 0
D86: 0 | F86: =D68 -> 0.57735027 | H86: прямоугольное | J86: 1 | L86: =F86 -> 0.57735027 | N86: 100
D87: =D85 -> 90 | F87: =F86 -> 0.57735027 | N87: 100
B89: Расширенная неопределенность U получается умножением суммарной стандартной неопределенности на коэффициент охвата k, который выбирается равным 1,65 при уровне доверия 95 % в предположении прямоугольного распределения вероятностей измеряемой величины:
G91: k= | H91: 1.65
B93: U= | C93: =H91*D68 -> 0.95262794 | D93: ˚
B94: Результат измерения записывается в виде:
B95: Угол между плоскостью переднего государственного регистрационного знака и опорной плоскостью при k = 1,65, Р = 95 | N95: =D81 -> 90 | O95: =H5 -> ± | P95: =C93 -> 0.95262794 | Q95: ˚
B96: Угол между плоскостью заднего государственного регистрационного знака и опорной плоскостьюпри k = 1,65, Р = 95% | N96: =D87 -> 90 | O96: =O95 -> ± | P96: =C93 -> 0.95262794 | Q96: ˚
B98: 1.3. Расчет неопределенности измерений высоты от опорной плоскости верхнего края государственного регистрационного знака
B99: Суммарная стандартная неопределенность измерения геометрических размеров:
E101: формула 10 ГОСТ 34100.3-2017/ISO/IEC Guide 98-3:2008
B103: где | D103: стандартная неопределенность измерения угла между плоскостью государственного регистрационного знака и опорной поверхностью, оцененная по типу А
D104: стандартная неопределенность измерения угла между плоскостью государственного регистра-ционного знака и опорной поверхностью, оцененная по типу B
B106: Стандартная неопределенность измерения геометрических размеров, оцененная по типу B
D110: где | F110: =I8 -> 0.2 | G110: мм | K110: абсолютная погрешность рулетки измерительной металлической RGK R-5 при проведении измерений в сантиметровом интервале
F111: =I9 -> 0.3 | G111: мм | K111: абсолютная погрешность рулетки измерительной металлической RGK R-5 при проведении измерений в дециметровом интервале
F112: =I10 -> (0,30+0,15(L-1)) | G112: , (0,30+0,15*(1-1))= | I112: =(0.3+0.15*(1-1)) -> 0.3 | J112: мм | K112: абсолютная погрешность рулетки измерительной металлической RGK R-5 при проведении измерений в интервале от 1 до 2м
B114: Стандартная неопределенность измерения размеров в сантиметровом интервале:
D116: = | E116: =F110/(3^(1/2)) -> 0.11547005 | F116: мм
B118: Стандартная неопределенность измерения размеров в дециметровом интервале, в интервале от 1 до 2м
D120: = | E120: =F111/(3^(1/2)) -> 0.17320508 | F120: мм
B122: Суммарная стандартная неопределенность измерения высоты от опорной плоскости верхнего края переднего государственного регистрационного знака
C123: =((E120^2)+0^2)^0.5 -> 0.17320508
B124: Суммарная стандартная неопределенность измерения высоты от опорной плоскости верхнего края заднего государственного регистрационного знака
C125: =((E120^2)+0^2)^0.5 -> 0.17320508
B126: Суммарная стандартная неопределенность измерения высоты от опорной плоскости нижнего края переднего государственного регистрационного знака
C127: =((E120^2)+0^2)^0.5 -> 0.17320508
B128: Суммарная стандартная неопределенность измерения высоты от опорной плоскости нижнего края заднего государственного регистрационного знака
C129: =((E120^2)+0^2)^0.5 -> 0.17320508
B131: Бюджет неопределенности.
B132: Формула для расчета определяемой величины:
B134: где | D134: результат измерения геометрического размера
D135: поправка на погрешность средства измерений
B137: Бюджет неопределенности для измерения высоты от опорной плоскости верхнего края переднего государственного регистрационного знака
...

Sheet Вводные
A1: п. А 1.2.2 прил. А ГОСТ 33670-2015 | B1: Угол между плоскостью государственного регистрационного знака и продольной плоскостью симметрии ТС, град | H1: Передний | I1: Задний | S1: мин | T1: макс
H2: 90 | I2: 90 | S2: 88 | T2: 92
B3: Угол между плоскостью государственного регистрационного знака и опорной поверхностью, град | H3: Передний | I3: Задний
H4: 90 | I4: 90 | S4: 62 | T4: 118
A5: п. А 1.2.3 прил. А ГОСТ 33670-2015 | B5: Высота от опорной плоскости верхнего края государственного регистрационного знака, мм | H5: Передний | I5: Задний
H6: 302 | I6: 600 | S6: 298 | T6: 1198
B7: Высота от опорной плоскости нижнего края государственного регистрационного знака, мм | H7: Передний | I7: Задний
H8: 500 | I8: 500 | S8: 298 | T8: 1198
A9: п. А 5.1.1.3 прил. А ГОСТ 33670-2015 | B9: Усилие на органе управления рабочей тормозной системы | H9: Ось 1 | I9: Ось 2 | J9: ед изм
H10: 490 | I10: 490 | J10: Н | S10: 10 | T10: 490
A11: п. А 5.1.1.4 прил. А ГОСТ 33670-2015 | B11: При проверках на стендах допускается относительная разность тормозных сил колес оси (в процентах от наибольшего значения) для осей ТС с дисковыми колесными тормозными механизмами не более 20% и для осей с барабанными колесными тормозными механизмами не более 25% | H11: Дисковые/дисковые
H12: Дисковые/барабанные
H13: Ось 1 | I13: Ось 2
B14: Относительная разность тормозных сил колес оси | H14: 0 | I14: 15 | J14: % | S14: 0 | T14: 25
A15: п. А 5.1.4.1.1 прил. А ГОСТ 33670-2015 | B15: Удельная тормозная сила для стояночной тормозной системы | S15: 0.17 | T15: 0.3
E16: ось 1 | F16: Левое колесо | I16: 2790 | J16: Н
F17: Правое колесо | I17: 2800 | J17: Н | K17: =(I17-I16)/I17 -> 0.0035714286 | L17: =(MAX(I16:I17)-MIN(I16:I17))/MAX(I16:I17) -> 0.0035714286
E18: ось 2 | F18: Левое колесо | I18: 2000 | J18: Н
F19: Правое колесо | I19: 2450 | J19: Н | K19: =(I19-I18)/I19 -> 0.18367347 | L19: =(MAX(I18:I19)-MIN(I18:I19))/MAX(I18:I19) -> 0.18367347
D20: Стояночная | F20: Левое колесо | I20: 2150 | J20: Н
F21: Правое колесо | I21: 1950 | J21: Н
A22: п. А 5.1.5 прил. АГОСТ 33670-2015 | B22: Усилие, прикладываемое к органу управления стояночной тормозной системой для приведения ее в действие, не должно превышать: - 589 Н - в случае ручного органа управления; - 688 Н - в случае ножного органа управления | H22: 490 | J22: Н | S22: 0 | T22: 568
A23: п. А 5 прил. А ГОСТ 33670-2015 | B23: Нагрузка на оси. | H23: Ось 1 | I23: Ось 2
H24: 995 | I24: 850
A25: п. А.8.9 прил. А ГОСТ 33670-2015 | B25: Требования к размещению фар ближнего света: по высоте над опорной поверхностью - не менее 500 мм, не более 1200 мм | H25: Левая | I25: Правая
H26: нижняя граница:
H27: 630 | I27: 630 | S27: 502 | T27: 1198
H28: верхняя граница:
H29: 780 | I29: 780 | S29: 502 | T29: 1198
A30: п. А.8.10.1 прил. А ГОСТ 33670-2015 | B30: Требования к размещению передних противотуманных фар. По ширине: та точка видимой поверхности в направлении исходной оси, которая в наибольшей степени удалена от средней продольной плоскости ТС, должна находиться на расстоянии не более 400 мм от края габаритной ширины ТС | H30: Левая | I30: Правая
H31: 100 | I31: 100 | S31: 0 | T31: 398
A32: п. А.8.10.2 прил. А ГОСТ 33670-2015 | B32: Требования к размещению передних противотуманных фар. По высоте: не менее 250 мм над поверхностью земли; для ТС категорий M1 и N1 - не более 800 мм над опорной поверхностью; для всех других категорий ТС максимальная высота не предусмотрена | H32: Левая | I32: Правая
H33: нижняя граница:
H34: 260 | I34: 260 | S34: 252 | T34: 798
H35: верхняя граница:
H36: 280 | I36: 280 | S36: 252 | T36: 798
A37: п. А.8.12.1 прил. А ГОСТ 33670-2015 | B37: Требования к размещению сигналов торможения: по ширине: для ТС категорий M1, N1, L2, L4 - L7 та точка видимой поверхности в направлении исходной оси, которая в наибольшей степени удалена от средней продольной плоскости ТС, должна находиться на расстоянии не более 400 мм от края габаритной ширины ТС; для ТС категорий L2, L5 - L7 в случае установки одного сигнала торможения его исходная ось должна лежать в средней продольной плоскости ТС, для ТС категории L4, если устанавливается третий сигнал торможения, то он должен быть установлен симметрично сигналу торможения, установленному на мотоцикле относительно средней продольной плоскости мотоцикла; для всех других категорий ТС та точка видимой поверхности в направлении исходной оси, которая в наименьшей степени удалена от средней продольной плоскости ТС, должна находиться на расстоянии не менее 600 мм от края габаритной ширины ТС. Это расстояние может быть уменьшено до 400 мм, если габаритная ширина ТС составляет менее 1300 мм | H37: Левая | I37: Правая
H38: 150 | I38: 150 | S38: 0 | T38: 400
H39: На кузове | J39: на Багажнике
A40: п. А.8.12.2 прил. А ГОСТ 33670-2015 | B40: Требования к размещению сигналов торможения: по высоте: над опорной поверхностью в пределах от 350 до 1500 мм (не менее 2100 мм, если соблюдение указанного требования невозможно из-за формы кузова, если факультативные огни не установлены). Если факультативные огни установлены, то они должны располагаться симметрично на как можно большем расстоянии по вертикали, которое допускается контуром кузова, но не менее чем 600 мм над обязательными огнями (кроме ТС категорий L). Для ТС категорий L1 - L3, L5 - L7 - не менее 250 мм и не более 1500 мм над опорной поверхностью; для ТС категории L4 - не менее 250 мм, не более 1200 мм над опорной поверхностью | H40: Левая | I40: Правая | J40: Левая | K40: Правая
H41: нижняя граница: | J41: нижняя граница:
H42: 890 | I42: 890 | J42: 860 | K42: 865 | S42: 352 | T42: 2098
H43: верхняя граница: | J43: верхняя граница:
H44: 955 | I44: 955 | J44: 935 | K44: 940 | S44: 352 | T44: 2098
A45: п. А.8.12.3 прил. А ГОСТ 33670-2015 | B45: Требования к размещению сигналов торможения: дополнительные сигналы торможения должны быть установлены не более 150 мм от нижнего края внешней поверхности или покрытия заднего стекла и не менее 850 мм от уровня опорной поверхности | H45: 1140 | I45: от опорной поверхности: | S45: 852 | T45: 2098
H46: 10 | I46: от нижнего края внешней поверхности или покрытия заднего стекла:
A47: п. А.8.12.4 прил. А ГОСТ 33670-2015 | B47: Требования к размещению сигналов торможения: допускается смещение оптического центра дополнительного сигнала торможения влево или вправо от средней продольной плоскости на расстояние не более 150 мм либо установка двух дополнительных сигналов торможения, которые в этом случае должны находиться как можно ближе к средней продольной плоскости, по одному устройству с каждой стороны этой плоскости | H47: 0 | S47: 0 | T47: 148
H48: Левая | I48: Правая
A49: п. А.8.13.2 прил. А ГОСТ 33670-2015 | B49: Требования к размещению задних противотуманных фонарей: по высоте над опорной поверхностью - не менее 250 мм, не более - 1000 мм. | H49: 850 | I49: 850 | J49: нижняя
H50: 940 | I50: 940 | J50: верхняя | S50: 252 | T50: 999
A51: п. А.8.20.6 прил. А ГОСТ 33670-2015 | B51: Требования к фарам ближнего и дальнего света и противотуманным: сила света каждой из фар в режиме "ближний свет", измеренная в вертикальной плоскости, проходящей через ось отсчета, должна быть не более 750 кд в направлении 34' вверх от положения левой части светотеневой границы и не менее 1600 кд в направлении 52' вниз от положения левой части светотеневой границы | K51: Левая | M51: Правая
K52: 34´ | L52: 643 | M52: 34´ | N52: 470 | O52: кд | S52: 100 | T52: 643
K53: 52´ | L53: 1600 | M53: 52´ | N53: 3800 | O53: кд | S53: 1600 | T53: 20000
A54: п. А.8.20.7 прил. А ГОСТ 33670-2015 | B54: Требования к фарам ближнего и дальнего света и противотуманным: максимальная сила света всех фар, которые могут быть включены одновременно в режиме "дальний свет", не должна превышать 300 000 кд | K54: Левая | M54: Правая
K55: 125000 | M55: 125000 | O55: кд | S55: 10000 | T55: 125000
K56: Расчетный показатель
K57: =M55+K55 -> 250000 | O57: кд
A58: п. А.8.22.1 прил. А ГОСТ 33670-2015 | B58: Указатели поворота должны работать в мигающем режиме. Частота следования проблесков должна находиться в пределах (1,5 ± 0,5) Гц, (90 ± 30 проблесков в минуту) | K58: 1.4 | O58: Гц | S58: 1.2 | T58: 1.8
A59: п. А.8.22.2 прил. А ГОСТ 33670-2015 | B59: Аварийная сигнализация должна обеспечивать синхронное включение всех указателей поворота в проблесковом режиме с частотой, указанной в пункте А.8.22.1 | K59: =K58 -> 1.4 | O59: Гц
A60: п. А.10.7.2 прил. А ГОСТ 33670-2015 | B60: Шина считается непригодной к эксплуатации при: остаточной глубине рисунка протектора шин (при отсутствии индикаторов износа) не более: - 0,8 мм - для ТС категорий L; - 1,0 мм - для ТС категорий N2, N3, O3, O4; - 1,6 мм - для ТС категорий M1, N1, O1, O2; - 2,0 мм - для ТС категорий M2, M3. | H60: Переднее левое колесо: | K60: 6 | L60: мм | S60: 1.8 | T60: 17
H61: Переднее правое колесо: | K61: 6 | L61: мм
H62: Заднее левое колесо: | K62: 6 | L62: мм
H63: Заднее правое колесо: | K63: 6 | L63: мм
A64: п. А.10.7.3 прил. А ГОСТ 33670-2015 | B64: Шина считается непригодной к эксплуатации при: остаточной глубине рисунка протектора зимних шин, предназначенных для эксплуатации на обледеневшем или заснеженном дорожном покрытии, маркированных знаком в виде горной вершины с тремя пиками и снежинки внутри нее (см. рисунок А.10.2), а также маркированных знаками "M+S", "M&S", "M S" (при отсутствии индикаторов износа), во время эксплуатации на указанном покрытии не более 4,0 мм. | H64: Переднее левое колесо: | L64: мм | S64: 4.1 | T64: 17
H65: Переднее правое колесо: | K65: =K64 -> 0 | L65: мм
H66: Заднее левое колесо: | K66: =K65 -> 0 | L66: мм
H67: Заднее правое колесо: | K67: =K66 -> 0 | L67: мм
A68: п. А.11.8 прил. А ГОСТ 33670-2015 | B68: Светопропускание ветрового стекла и стекол, через которые обеспечивается передняя обзорность для водителя, должно составлять не менее 70%. В верхней части ветрового стекла допускается наличие светозащитной полосы, выполненной в массе стекла, либо крепление светозащитной полосы прозрачной цветной пленки: на ТС категорий M1, M2 и N1, а также L6 и L7 (с кузовом закрытого типа) - шириной не более 140 мм, а на ТС категорий M3, N2 и N3 - шириной, не превышающей минимального расстояния между верхним краем ветрового стекла и верхней границей зоны его очистки стеклоочистителем. Если тонировка выполнена в массе стекла, ширина затеняющей полосы должна соответствовать установленной изготовителем ТС. Светопропускание светозащитной полосы не нормируется | J68: Ветровое стекло | M68: 82.3 | N68: % | S68: 72 | T68: 90
J69: Правое | M69: 80.7 | N69: %
J70: Форточка передняя правая | N70: %
J71: Левое | M71: 80.9 | N71: %
J72: Форточка передняя левая | N72: %
J73: Ширина светозащитной полосы | M73: 90 | N73: мм | S73: 0 | T73: 138
A74: п. А.12.3 прил. А ГОСТ 33670-2015 | B74: Скорость ТС по показаниям спидометра не должна быть меньше его фактической скорости | G74: Скорость на спидометре автомобиля | K74: 20 | L74: км/ч | S74: 6 | T74: 29
G75: Фактическая скорость | K75: 20 | L75: км/ч
A76: п. А 16.9 прил. А ГОСТ 33670-2015 | B76: Концы бамперов загибаются в направлении к кузову так, чтобы с ними не мог соприкоснуться шар диаметром 100 мм, и расстояние между краем бампера и кузовом не превышает 20 мм. | G76: Расстояние между краем бампера и кузовом | I76: 1 | J76: мм
S77: 0 | T77: 1.5
B78: Для ТС категории M1, N1, L6 и L7 не выступают за наружную поверхность кузова ручки дверей и багажника более чем на 40 мм, остальные выступающие элементы - более чем на 30 мм | G78: Выступание ручек дверей и багажника | I78: 25 | J78: мм | S78: 0 | T78: 39
G79: Остальные выступающие элементы | I79: 16 | J79: мм | K79: Передние боковые повторители
A80: п. А 21.7 прил. А ГОСТ 33670-2015 | B80: Содержание оксида углерода (CO) в отработавших газах ТС с бензиновыми и газовыми двигателями в режиме холостого хода на минимальной и повышенной частотах вращения коленчатого вала двигателя не должно превышать значений, установленных изготовителем для целей оценки соответствия типа ТС перед его выпуском в обращение, а при отсутствии таких данных - не должно превышать значений, указанных в таблице А.21.1 | L80: Min обор: CO, % | N80: Max обор: CO, %
L81: 0 | N81: 0 | S81: 0 | T81: 0.01 | U81: =T81+0.01 -> 0.02 | V81: =U81+0.01 -> 0.03 | W81: =V81+0.01 -> 0.04 | X81: =W81+0.01 -> 0.05 | Y81: =X81+0.01 -> 0.06 | Z81: =Y81+0.01 -> 0.07 | AA81: =Z81+0.01 -> 0.08 | AB81: =AA81+0.01 -> 0.09 | ... AI81: =AH81+0.01 -> 0.16 | AJ81: -
A82: п. А 21.8 прил. А ГОСТ 33670-2015 | B82: Дымность отработавших газов ТС с дизелями в режиме свободного ускорения не должна превышать значений коэффициента поглощения света, указанного в документах, удостоверяющих соответствие ТС Правилам ООН N 24 [54], либо значений, указанных на знаке официального утверждения, нанесенном на двигатель или ТС, либо установленных изготовителем ТС в эксплуатационной документации | J82: 1 | K82: - | S82: 0 | T82: =S82+0.01 -> 0.01 | U82: =T82+0.01 -> 0.02 | V82: =U82+0.01 -> 0.03 | W82: =V82+0.01 -> 0.04 | X82: =W82+0.01 -> 0.05 | Y82: =X82+0.01 -> 0.06 | Z82: =Y82+0.01 -> 0.07 | AA82: =Z82+0.01 -> 0.08 | ... ES82: =ER82+0.01 -> 1.3 | ET82: -
J83: 2 | K83: -
J84: 3 | K84: -
J85: 4 | K85: -
J86: 5 | K86: -
J87: 6 | K87: -
A88: п. А.23.1 прил. А, приложение В, ГОСТ 33670-2015 | B88: Уровень шума выпуска отработавших газов ТС, измеренный на расстоянии 0,5 м от среза выпускной трубы под углом 45° +/- 10° к оси потока газа на неподвижном ТС при работе двигателя на холостом ходу при поддержании постоянной целевой частоты вращения коленчатого вала двигателя и в режиме замедления его вращения от целевой частоты до минимальной частоты холостого хода, не должен превышать более чем на 5 дБ(A) значений, установленных изготовителем ТС, а при отсутствии этих данных — значений, указанных в таблице А.23.1 | K88: На холостом ходу при поддержании постоянной целевой частоты вращения | N88: В режиме замедления от целевой частоты до минимальной частоты холостого хода | Q88: ед. изм.
K89: 82 | N89: 80 | Q89: дБ | S89: 73 | T89: 93
A90: п. А.24.3 прил. А ГОСТ 33670-2015 | B90: Суммарный люфт в рулевом управлении не должен превышать предельных значений, установленных изготовителем ТС, а при отсутствии указанных данных следующих предельных значений: - ТС категорий M2 и N2, созданные на базе агрегатов ТС категории M1, - 10°; - ТС категорий M2 и M3 - 20°; - ТС категорий N - 25° | I90: 9 | J90: град | S90: 0 | T90: 9.5
A93: п. 2.2.1, 2.2.5 ГОСТ 22748-77 | B93: Габаритная длина | M93: 4377 | N93: мм | S93: 0 | T93: 11998
A94: п. 2.2.1, 2.2.21 ГОСТ 22748-77 | B94: Габаритная ширина | M94: 1700 | N94: мм | S94: 0 | T94: 2598
A95: п. 2.2.1, 2.2.27 ГОСТ 22748-77 | B95: Габаритная высота | M95: 1470 | N95: мм | S95: 0 | T95: 3998
A96: ГОСТ 33987-2016, Приложение Г | B96: Масса | L96: 1240 | M96: кг | S96: 0 | T96: 3495
G430: =Вводные!H47 -> 0

Sheet Правило
I3: Общество с ограниченной ответственностью «А-Профит»
I4: (ООО «А-Профит»)
I5: Адрес места нахождения юридического лица:
I6: 690074, Россия, Приморский край, г. Владивосток, ул. Снеговая, д. 64, офис 1
I7: Тел.: 89240037850, e-mail: a_profit_lab@mail.ru
I9: Испытательная лаборатория ООО «А-Профит»
I10: (ООО «А-Профит»)
I11: Адреса мест осуществления деятельности:
I12: 690074, Россия, Приморский край, г. Владивосток, ул. Снеговая, д. 64
I13: Тел.: 89240037850, e-mail: a_profit_lab@mail.ru
M16: УТВЕРЖДАЮ
M18: Руководитель ИЛ ООО «А-Профит»
O19: А.Г. Луговой
M20: Подпись | O20: И.О. Фамилия
M21: =M28 -> 08.05.2025 г.
G28: Протокол № | I28: АВМ00 | K28: от | M28: 08.05.2025 г.
C29: идентификации, технической экспертизы конструкции, исследований, испытаний и измерений транспортного средства на соответствия предъявляемым требованиям ТР ТС 018/2011 к Единичным транспортным средствам
H73: Результаты исследований, испытаний и измерений относятся только к образцу (объекту), предоставленному заказчиком.
H74: Результаты исследований, испытаний и измерений относятся только к образцу (объекту), прошедшему исследования,
H75: испытания и измерения в испытательной лаборатории ООО «А-Профит».
H76: Протокол не может быть частично воспроизведен без письменного разрешения лаборатории.
H77: Испытательная лаборатория (центр) несет ответственность за всю информацию, предоставленную в протоколе
H78: испытаний, за исключением случаев, когда информация предоставлена заказчиком.
A80: Протокол идентификации, технической экспертизы конструкции, исследований, испытаний и измерений транспортного средства на соответствия предъявляемым требованиям
E81: ТР ТС 018/2011 к Единичным транспортным средствам № | J81: =I28 -> АВМ00 | L81: от | M81: =M28 -> 08.05.2025 г.
I83: 1. ОБЪЕКТ ИСПЫТАНИЙ
B84: Таблица 1.1 Общие сведения
A85: Наименование образца испытаний (идентификация объекта, поступившего на испытания: марка, тип/обозначение, заводской номер, другая уникальная идентифицирующая информация) | F85: Транспортное средство:
F86: Марка | K86: HAVAL
F87: коммерческое название | K87: F7
F88: тип | K88: CC6475UM22B
F89: Индефикационный номер (VIN) | K89: XZGFF06A9PA346000
F90: Гос. Номер
F91: Категория | K91: М1
A92: Наименование и контактные данные заказчика* (для юридических лиц указывают наименование, юридический адрес и фактический адрес места осуществления деятельности; для ИП указывают инициалы, фамилию, адрес регистрации; для физического лица указывают инициалы, фамилию, почтовый адрес) | F92: ООО «А-Профит» Адрес места нахождения юридического лица: 690074, Россия, Приморский край, г. Владивосток, ул. Снеговая, д. 64, офис 1 Адреса мест осуществления деятельности: 690074, Россия, Приморский край, г. Владивосток, ул. Снеговая, д. 64
A97: Наименование и адрес изготовителя (юридический адрес и фактический адрес места осуществления деятельности) | F97: Изготовитель и его адрес: ООО "ХАВЕЙЛ МОТОР МАНУФЭКЧУРИНГ РУС" Адрес: г. Москва, Профсоюзная улица, д. 65, корпус 1 Сборочный завод и его адрес: Завод HAVAL Адрес: 301637, Российская Федерация, Тульская область, Узловский Район, ул. Индустриальная (Индустриальный парк тер.), здание 11
A100: Данные об отборе образца | F100: Образец предоставлен заказчиком, ИЛ не несет ответственности за данные отбора образца
A102: Дата получения образца | F102: =M28 -> 08.05.2025 г.
A103: Дата(ы) начала и окончания испытаний | F103: =M28 -> 08.05.2025 г.
A104: Цель осуществления проведения испытаний | F104: Оценка соответствия определяемых в рамках испытаний характеристик единичного транспортного средства требованиям TP TC 018/2011
A106: Идентификация применяемого метода | F106: ГОСТ 33670-2015, приложение А п. А 1.1, п. А 1.2, п. А 1.2.1, п. А 1.2.2, п. А 1.2.3, п. А 1.2.4, п. А 2.1, п. А 3.1, п. А 3.2, п. А 5.1.1.1, п. А 5.1.1.2, п. А.5.1.1.3, п. А 5.1.1.4, п. А 5.1.2.1, п. А 5.1.2.2, п. А 5.1.3.1, п. А 5.1.3.2, п. А 5.1.4, п. А 5.1.4.1- 5.1.4.2, п. А 5.1.4.3, п. А 5.1.5, п. А 5.2, п. А 5.3, п. А 5.4, п. А 5.5.1.1, п. А 5.5.1.1.1, п. А 5.5.1.1.2, п. А 5.5.1.2, п. А 5.5.1.3, п. А 5.5.2.1, п. А 5.5.2.2, п. А 5.7, п. А 5.8, п. А 5.9, п. А 5.11.1, п. А 5.11.2, п. А 5.11.3, п. А 5.11.4, п. А 5.11.5, п. А 5.11.6, п. А 5.11.7, п. А 5.11.8, п. А 5.12, п. А 5.13, п. А 5.15.1, п. А 5.15.2, п. А.5.16, п. А 6.1, п. А 6.2, п. А 6.3, п. А 6.4, п. А 6.5, п. А 6.6, п. А 6.7, п. А 6.8, п. А 6.9, п. А 7.1, п. А 7.2, п. А 7.3, п. А 7.4, п. А 7.5, п. А 7.6, п. А 7.7, п. А.8.1, п. А.8.2, п. А.8.3, п. А.8.4, п. А.8.5, п. А.8.6, п. А.8.7, п. А.8.8, п. А.8.9, п. А.8.10.1, п. А.8.10.2, п. А.8.10.3, п. А.8.11, п. А.8.12.1, п. А.8.12.2, п. А.8.12.3, п. А.8.12.4, п. А.8.13.1, п. А.8.13.2, п. А.8.14, п. А.8.15, п. А.8.16, п. А.8.17, п. А.8.18.2, п. А.8.18.3, п. А.8.18.4, п. А.8.19, п. А.8.20.1, п. А.8.20.2, п. А.8.20.3, п. А.8.20.4, п. А.8.20.5, п. А.8.20.6, п. А.8.20.7, п. А.8.20.8, п. А.8.21, п. А.8.22.1, п. А.8.22.2, п. А.8.22.3, п. А.8.23.1, п. А.8.23.2, п. А.8.24.1, п. А.8.24.2, п. А.8.24.3, п. А.8.25, п. А.8.26, п. А.8.27, п. А.8.28, п. А.10.1, п. А.10.2, п. А.10.3, п. А.10.4 п. А.10.5, п. А.10.6, п. А.10.7.1, п. А.10.7.2, п. А.10.7.3, п. А.10.7.4, п. А.10.7.5, п. А.10.8.1, п. А.10.8.2, п. А.10.8.3, п. А.10.8.4, п. А.10.9.1, п. А.10.9.2, п. А.10.9.2.1, п. А.10.9.2.2, п. А.10.9.2.3, п. А.10.9.2.4, п. А.10.9.2.5, п. А.10.9.3, А.11.1, п. А.11.2, п. А.11.3, п. А.11.4 п. А.11.5, п. А.11.6, п. А.11.8, п. А.11.9, п. А.11.10, п. А.11.11, п. А.11.12 п. А.11.13, п. А.11.14, п. А.11.15, п. А.11.16, п. А.11.17, п. А 12.1, п. А 12.2, п. А 12.3, п. А 13.1, п. А 13.2, п. А 13.3.1, п. А 13.3.2, п. А 13.4, п. А 13.5, п. А 13.6, п. А 13.7.1, п. А 13.7.2, п. А 13.8, п. А 13.9, п. А 13.10, п. А 13.11, п. А 13.12, п. А 13.13, п. А 13.14, п. А 13.15, п. А 13.16, п. А 13.17, п. А 13.19.1, п. А 13.19.2, п. А 13.19.3, п. А 13.19.4, , п. А 13.20, п. А 13.21, п. А 14.1, п. А 14.2, п. А 14.3, п. А 15.1, п. А 15.2, п. А 15.3, п. А 16.1, п. А 16.2, п. А 16.3, п. А 16.4, п. А 16.5, п. А 16.6, п. А 16.7, п. А 16.8, п. А 16.9, п. А 16.11, п. А 16.12, п. А 16.13, п. А 16.14, п. А 16.15, п. А 16.16, п. А 16.17, п. А 16.18, п. А 17.1, п. А 17.2, п. А 17.3, п. А 18.1, п. А 18.2, п. А 18.3, п. А 18.4, п. А 18.4.1, п. А 18.4.2, п. А 18.4.3, п. А 18.4.4, п. А 18.5, п. А.20.1, п. А.20.2, п. А.20.3, п. А.20.5, п. А.20.5.1, п. А.20.5.2, п. А.20.5.3, п. А.20.6, п. А.20.7, п. А.20.8, п. А 21.1, п. А 21.2, п. А 21.3, п. А 21.4, п. А 21.5, п. А 21.6, п. А 21.7, п. А 21.8, п. А 21.9, п. А 22.1, п. А 22.2, п. А 22.3, п. А 22.4, п. А 22.5.1, п. А 22.5.2, п. А 22.5.3, п. А 22.5.4, п. А 22.5.5, п. А 22.5.6.1, п. А 22.5.6.2, п. А 22.5.6.3, п. А 23.1, п. А 23.2, п. А 24.1, п. А 24.2, п. А 24.3, п. А 24.4, п. А 24.5, п. А 24.6, п. А 26.1, п. А 26.2, п. А 26.3, п. А 26.4, п. А 26.5, п. А 26.6, п. А 26.7, п. А 26.8, п. А 26.9, п. А 26.10, п. А 26.11, п. А 26.12, п. А 26.13, п. А 26.14, п. А 26.15, п. А 26.16, п. А 26.17, п. А.27.1, п. А.27.2, п. А.27.3, п. А.27.4, п. А.27.5 Приложение В, Приложение Г, ГОСТ 33997-2016 п. 5.11.14, СТБ 914-99 Приложение Е, п.Е.4.7, ГОСТ 22748-77, п. 2.2.1, п. 2.2.5, п. 2.2.21, п. 2.2.27, ГОСТ 33987-2016, Приложение В, Приложение Г
A129: Место (места) осуществления испытаний (адрес места проведения испытаний) | F129: 690003, Россия, Приморский край, г. Владивосток, ул. Снеговая, д. 64, офис 1
B131: * Информация предоставлена заказчиком, который несет полную ответственность за эти данные
I133: 2. УСЛОВИЯ ПРОВЕДЕНИЯ ИСПЫТАНИЙ
B134: Таблица 2.1 Описание условий окружающей среды и параметров электрической сети
A135: Наименование показателя | F135: Значение (при проведении испытаний)
A136: Условия проведения испытаний
A137: Температура окружающей среды, °С
A138: Относительная влажность, %
A139: Атмосферное давление, кПа
A140: Условия проведения испытаний в дорожных условиях
A141: Температура окружающей среды, °С
A142: Относительная влажность, %
A143: Атмосферное давление, кПа
A144: Параметры электрической сети
A145: Частота электрической сети, Гц
A146: Напряжение в сети, В | F146: Фаза а-ноль | K146: Фаза b-ноль | O146: Фаза c-ноль
F148: Фаза b-фаза c | K148: Фаза b-фаза c | O148: Фаза a-фаза c
B150: Таблица 2.2 Проверка выполнения требований к единичным ТС
A151: Требования | F151: Отметка о соответствии/несоответствии
A152: Соответствие требованиям п. 3.1. ГОСТа 33670-2015 | F152: соответствует
A153: Соответствие требованиям п. 3.2. ГОСТа 33670-2015 | F153: соответствует
A154: Соответствие требованиям п. 3.3. ГОСТа 33670-2015 | F154: соответствует
A156: Протокол идентификации, технической экспертизы конструкции, исследований, испытаний и измерений транспортного средства на соответствия предъявляемым требованиям
E157: ТР ТС 018/2011 к Единичным транспортным средствам № | J157: =J81 -> АВМ00 | L157: от | M157: =M81 -> 08.05.2025 г.
H159: 3. СВЕДЕНИЯ О ПРИМЕНЯЕМОМ ОБОРУДОВАНИИ
A160: Средства измерения
A161: № п/п | B161: Наименование испытательного оборудования, средств измерения | D161: Диапазон измерений | F161: Класс точности (разряд), погрешность | M161: Сведения о результатах поверки СИ (дата, срок действия) | Q161: Заводской или инвентарный номер
A162: 1 | B162: Измеритель параметров света фар автотранспортных средств ИПФ-1 | D162: от 0 до 2° 20’ (угол наклона) от 200 до 125000 кД (сила света) от 1 до 2Гц (частота проблесков) | F162: Абсолютная погрешность измерения углов наклона светотеневой границы светового пучка фары в вертикальной плоскости: ±0,1% Абсолютная погрешность установки оптической камеры измерителя в горизонтальной плоскости: ±30' Относительная погрешность измерения силы света внешних световых источников: ±15% Абсолютная погрешность измерения частоты следования световых проблесков фонарей указателей поворота: ±0,1 Гц | M162: 02.08.2024г., 12 мес. | Q162: № СИ001
A163: 2 | B163: Преобразователь измерительный угла поворота «ИСЛ-М» | D163: от 0 до 50° | F163: Максимальная погрешность измерения суммарного люфта: ±0,5° | M163: 05.06.2024, 12 мес. | Q163: № СИ002
A164: 3 | B164: Дымомер АВГ-1Д-4.01 | D164: от 0,00 до ∞ от 0,0 до 100,0% от 0 до 6000 мин 0 до +100°С | F164: абсолютная погрешность при коэффициенте поглощения 1,6-1,8м-1: ±0,05 Погрешность: ±1,0 % Погрешность: ±2,5 % Погрешность: ±2,5 % | M164: 17.06.2024 г., 12 мес. | Q164: № СИ003
A165: 4 | B165: Измеритель светопропускания стекол "ТОНИК" | D165: от 4 до 100% | F165: Абсолютная погрешность ±2,0% | M165: 02.08.2024 г., 12 мес. | Q165: № СИ004
A166: 5 | B166: Газоанализатор многокомпонентный «Автотест-02.02» 0 кл | D166: Углеводороды от 0 до 2000 млн1 оксид углерода от 0 до 5%, диоксид углерода от 0 до 16%, кислород от 0 до 21%, окислы азота от 0 до 5000 млн1 λ-параметр 0,5-2,00 частота оборотов от 0-8000 мин1 температура масла от 0 до 125°С | F166: Абсолютная погрешность: ±10млн1, относительная погрешность: ±5% Абсолютная погрешность: ±0,03%, относительная погрешность: ±3% Абсолютная погрешность: ±0,5%, относительная погрешность: ±4% Абсолютная погрешность: ±0,1%, относительная погрешность: ±3% Абсолютная погрешность: ±50млн1, относительная погрешность: ±5% Не нормируется Относительная погрешность: ±2,5% Абсолютная погрешность: ±2°С | M166: 23.07.2024 г., 12 мес. | Q166: № СИ005
A167: 6 | B167: Стенд тормозной СТН 13000.01 | D167: от 0 до 30 кН (тормозная сила) от 0 до 1000Н (сила на органе управления) от 0 до 13000кг (масса ТС) | F167: Относительная погрешность: ±3% (тормозная сила) ±5% (сила на органе управления) ±3% (масса ТС) | M167: 13.09.2024 г., 12 мес. | Q167: № СИ006
A168: 7 | B168: Рулетка Р30У2К 30м | D168: от 0 до 30м | F168: Класс 2 Допускаемое отклонение: мм±0,15, см±0,20, дц±0,30, м ±[0,30+0,15(L-l)] | M168: 16.09.2024 г., 12 мес. | Q168: № СИ007
A169: 8 | B169: Штангенциркуль ШЦ-1-150 0,05 | D169: от 0 до 100мм | F169: Погрешность показаний: ±0,05мм | M169: 20.06.2024, 12 мес. | Q169: № СИ008
A170: 9 | B170: Угломер маятниковый З УРИ-М | D170: от 0 до 360° | F170: Погрешность показаний: ±1º | M170: 22.08.2024 г., 12 мес. | Q170: № СИ009
A171: 10 | B171: Прибор комбинированный Testo 622 | D171: от-10 до +60 °С от 10 до 95 % от 30 до 120 кПа | F171: Погрешность: ±0,4 °С ±3 % ±0,5 кПа | M171: 30.08.2024 г., 12 мес. | Q171: № СИ010
A172: 11 | B172: Термометр инфракрасный Testo 830-Т 1 | D172: от -30 до +400°C | F172: Погрешность показаний: ±1,5°C (от +0,1 до +400°C) ±2,0°C (от -30 до 0°C) | M172: 28.08.2024, 12 мес. | Q172: № СИ011
A173: 12 | B173: Секундомер механический типа СОСпр-2б-2-000 | D173: от 0 до 60с, от 0 до 60мин | F173: Класс точности второй Погрешность показаний при измерении интервала времени 60 мин: при температуре (20±5)°C ±1,8с, в диапазоне рабочих температур – в пределах ±5,4 с (диапазон рабочих температур: от -20°C до +40°C) | M173: 12.11.2024 г., 12 мес. | Q173: №СИ012
... A179: 18 | B179: Весы автомобильные подкладные ИСТОК-30-4П/10кг | D179: от 200 до 30000кг | F179: Пределы допускаемой погрешности: от 200 до 5000 вкл. кг ± 5 кг св. 5000 до 20000 вкл. кг ±10кг св. 20000 до 30000 вкл. кг ±15кг) | M179: 16.09.2024г., 12 мес. | Q179: № СИ018
A180: Протокол идентификации, технической экспертизы конструкции, исследований, испытаний и измерений транспортного средства на соответствия предъявляемым требованиям
E181: ТР ТС 018/2011 к Единичным транспортным средствам № | J181: =J157 -> АВМ00 | L181: от | M181: =M157 -> 08.05.2025 г.
A183: № п/п | B183: Наименование испытательного оборудования, средств измерения | D183: Диапазон измерений | F183: Класс точности (разряд), погрешность | M183: Сведения о результатах поверки СИ (дата, срок действия) | Q183: Заводской или инвентарный номер
A184: 19 | B184: Весы неавтоматического действия МП150 ВДА Ф-3 | D184: от 0,04 кг до 150 кг | F184: Класс 3 Допустимое отклонение: 0,01 кг | M184: 23.01.2025г., 12 мес. | Q184: № СИ019
A185: 20 | B185: Угломер с нониусом 4УМ | D185: от 0 до 180° | F185: Погрешность показаний: ± 0,10´ | M185: 22.08.2024 г., 12 мес. | Q185: № СИ020
A186: 21 | B186: Рейка нивелирная телескопическая Vega TS5M с уровнем 5 м | D186: от 0 до 5000мм | F186: допустимое отклонение не более: длины деления ±0,5мм, метрового интервала ±1,0мм, погрешность совмещения нуля шкалы рейки с плоскостью пятки рейки ±0,5мм, отклонение от перпендикулярности плоскости пятки рейки к продольной оси рейки 0,5мм | M186: 25.07.2024г., 12 мес. | Q186: № СИ021
A187: 22 | B187: Уровень брусковый 250мм 0,02мм/м | D187: 250 мм с ценой деления 0,02 мм/м | F187: Пределы допускаемой погрешности ±0,006 мм/м | M187: 22.08.2024г., 12 мес. | Q187: № СИ022
A188: 23 | B188: Линейка измерительная металлическая L300 | D188: от 0 до 300 мм | F188: Погрешность показаний: ±0,10 мм | M188: 22.08.2024 г., 12 мес. | Q188: № СИ023
A189: 24 | B189: Линейка измерительная металлическая L500 | D189: от 0 до 500 мм | F189: Погрешность показаний: ±0,15 мм | M189: 22.08.2024 г., 12 мес. | Q189: № СИ024
A190: 25 | B190: Линейка измерительная металлическая L1000 | D190: от 0 до 1000 мм | F190: Погрешность показаний: ±0,20 мм | M190: 22.08.2024 г., 12 мес. | Q190: № СИ025
A191: 26 | B191: Манометр МП 3-УФ 1,0 Мпа | D191: от 0 до 1,0 Мпа | F191: Погрешность показаний: ±1,5% | M191: 02.11.2024 г., 24 мес. | Q191: № СИ026
A192: 27 | B192: Мультиметр цифровой CEM DT-9908 | D192: от 200 мВ до 1000 В от 2В до 700 В от 200 Ом до 20,0 Мом | F192: Погрешность показаний: ±0,5 % показ ±2 (200мВ - 200В) ±0,8 % показ ±2 (1000В) ±1,0 % показ ±3 (2В - 200В) ±1,2 % показ ±5 (700В) ±1,0 % показ ± 4 (200 Ом) ±1,0 % показ ± 2 (2кОм) ±1,2 % показ ± 2 (20кОм-2МОм) ±2,0% показ ±5 (20МОм) | M192: 31.07.2024 г., 12 мес | Q192: № СИ027
A193: 28 | B193: Течеискатель-сигнализатор «ФП-12» | D193: Порог чувствительности в режиме течеискания, объемная доля в %, по метану (CH4) 0,001; по пропану (C3H8) 0,003 Порог срабатывания сигнализации, объемная доля в %, по метану (CH4) 1,0, по пропану (C3H8) 0,4 | F193: Пределы основной абсолютной погрешности, объемная доля в %, по метану ± 0,40; по пропану ± 0,16 | M193: 25.12.2024 г., 12 мес. | Q193: № СИ028
A194: 29 | B194: Секундомер электронный VA-SW01 | D194: от 0,01 с до 29 мин 59,99 с | F194: Погрешность ±(〖10〗^█(-5@) ·Тх + 0,05+емр) | M194: 28.05.2024 г., 12 мес | Q194: № СИ029
A195: 30 | B195: Манометр шинный МД214 | D195: от 50 до З00кПа | F195: Погрешность показаний: ±10кПа | M195: 18.04.2025 г., 12 мес. | Q195: № СИ030
... A200: 35 | B200: Рулетка RGK R-5 | D200: от 0 до 5 м | F200: Класс 2 Допускаемое отклонение: мм±0,15, см±0,20, дц±0,30, м ±[0,30+0,15(L-l)] | M200: 19.11.2024 г., 12 мес. | Q200: № СИ035
A201: Испытательное оборудование
A202: № п/п | B202: Наименование испытательного оборудования | E202: Технические характеристики ИО | M202: Сведения о результатах аттестации ИО (дата, срок действия) | Q202: Заводской или инвентарный номер
A203: 36 | B203: Шар испытательный неметаллический D 100 мм ТД-056.100 | E203: Диаметр – 100±3 мм | M203: 25.09.2024 г., 24 мес. | Q203: № ИО001
...

Sheet Оборудование
A1: Текущая дата | C1: =TODAY() -> 46310 | E1: TRUE
H2: 3. СВЕДЕНИЯ О ПРИМЕНЯЕМОМ ОБОРУДОВАНИИ
A3: Средства измерения
A4: № п/п | B4: Наименование испытательного оборудования, средств измерения | D4: Диапазон измерений | F4: Класс точности (разряд), погрешность | M4: Сведения о результатах поверки СИ (дата, срок действия) | Q4: Заводской или инвентарный номер
A5: 1 | B5: Измеритель параметров света фар автотранспортных средств ИПФ-01 | D5: от 0 до 2° 20’ (угол наклона) от 200 до 125000 кД (сила света) от 1 до 2Гц (частота проблесков) | F5: Абсолютная погрешность измерения углов наклона светотеневой границы светового пучка фары в вертикальной плоскости: ±0,1% Абсолютная погрешность установки оптической камеры измерителя в горизонтальной плоскости: ±30 ' Относительная погрешность измерения силы света внешних световых источников: ±15% Абсолютная погрешность измерения частоты следования световых проблесков фонарей указателей поворота: ±0,1 Гц | M5: Св-во № С-АЭ/06-08-2025/ 453157456 от | Q5: № СИ001
M6: 45875 | O6: г., 12 мес.
A7: 2 | B7: Преобразователь измерительный угла поворота «ИСЛ-М» | D7: от 0 до 50° | F7: Максимальная погрешность измерения суммарного люфта: ±0,5° | M7: Св-во № С-АЭ/02-06-2025/ 436547222 от | Q7: № СИ002
M8: 45810 | O8: г., 12 мес.
A9: 3 | B9: Дымомер АВГ-1Д-4.01 | D9: от 0,00 до ∞ от 0,0 до 100,0% от 0 до 6000 мин 0 до +100°С | F9: абсолютная погрешность при коэффициенте поглощения 1,6-1,8м-1: ±0,05 Погрешность: ±1,0 % Погрешность: ±2,5 % Погрешность: ±2,5 % | M9: Св-во № С-АЭ/02-06-2025/ 436579464 от | Q9: № СИ003
M10: 45810 | O10: г., 12 мес.
A11: 4 | B11: Измеритель светопропускания стекол "ТОНИК" | D11: от 4 до 100% | F11: Абсолютная погрешность ±2,0% | M11: Св-во № С-АЭ/06-08-2025/ 453155401 от | Q11: № СИ004
M12: 45875 | O12: г., 12 мес.
A13: 5 | B13: Газоанализатор многокомпонентный «Автотест-02.02» 0 кл | D13: Углеводороды от 0 до 2000 млн1 оксид углерода от 0 до 5%, диоксид углерода от 0 до 16%, кислород от 0 до 21%, окислы азота от 0 до 5000 млн1 λ-параметр 0,5-2,00 частота оборотов от 0-8000 мин1 температура масла от 0 до 125°С | F13: Абсолютная погрешность: ±10млн1, относительная погрешность: ±5% Абсолютная погрешность: ±0,03%, относительная погрешность: ±3% Абсолютная погрешность: ±0,5%, относительная погрешность: ±4% Абсолютная погрешность: ±0,1%, относительная погрешность: ±3% Абсолютная погрешность: ±50млн1, относительная погрешность: ±5% Не нормируется Относительная погрешность: ±2,5% Абсолютная погрешность: ±2°С | M13: Св-во № С-АЭ/10-07-2025/ 446406612 от | Q13: № СИ005
M14: 45848 | O14: г., 12 мес.
A15: 6 | B15: Стенд тормозной СТН 13000.01 | D15: от 0 до 30 кН (тормозная сила) от 0 до 1000Н (сила на органе управления) от 0 до 13000кг (масса ТС) | F15: Относительная погрешность: ±3% (тормозная сила) ±5% (сила на органе управления) ±3% (масса ТС) | M15: Св-во№ С-АЭ/05-09-2025/ 461489585 от | Q15: № СИ006
M16: 45905 | O16: г., 12 мес.
A17: 7 | B17: Рулетка Р30У2К 30м | D17: от 0 до 30м | F17: Класс 2 Допускаемое отклонение: мм±0,15, см±0,20, дц±0,30, м ±[0,30+0,15(L-l)] | M17: Св-во № С-АЭ/05-09-2025/ 461447340 от | Q17: № СИ007
M18: 45905 | O18: г., 12 мес.
A19: 8 | B19: Штангенциркуль ШЦ-1-150 0,05 | D19: от 0 до 100мм | F19: Погрешность показаний: ±0,05мм | M19: Св-во № С-АЭ/02-06-2025/ 436547220 от | Q19: № СИ008
M20: 45810 | O20: г., 12 мес.
A21: 9 | B21: Угломер маятниковый З УРИ-М | D21: от 0 до 360° | F21: Погрешность показаний: ±1º | M21: Св-во № С-АЭ/21-08-2025/ 458005858 от | Q21: № СИ009
M22: 45890 | O22: г., 12 мес.
A23: 10 | B23: Прибор комбинированный Testo 622 | D23: от-10 до +60 °С от 10 до 95 % от 30 до 120 кПа | F23: Погрешность: ±0,4 °С ±3 % ±0,5 кПа | M23: Св-во № С-ВЦЛ/01-09-2025/ 460740052 от | Q23: № СИ010
M24: 45901 | O24: г., 12 мес.
A25: 11 | B25: Термометр инфракрасный Testo 830-Т 1 | D25: от -30 до +400°C | F25: Погрешность показаний: ±1,5°C (от +0,1 до +400°C) ±2,0°C (от -30 до 0°C) | M25: Св-во № С-АЭ/19-08-2025/ 457455641 от | Q25: № СИ011
M26: 45888 | O26: г., 12 мес.
A27: 12 | B27: Измеритель скорости и длины ИСД-5.1 | D27: от 0,5 до 180 км/ч | F27: Пределы допускаемой относительной среднеквадратичной погрешности измерения скорости ±0,15% и длины ±0,1% - на длине не менее 20 м | M27: Св-во № С-С/15-10-2025/474327055 от | Q27: № СИ013
M28: 45945 | O28: г., 12 мес.
A29: 13 | B29: Шумомер-анализатор спектра портативный ОКТАВА-111 + микрофонный предусилитель Р200 | D29: от 19 до 141дБ | F29: Класс 1 Погрешность показаний: ±0,5 дБ | M29: Св-во № С-АЭ/19-08-2025/ 457406029 от | Q29: № СИ014
M30: 45888 | O30: г., 12 мес.
A31: 14 | B31: Калибратор акустический AK-1000 | D31: 1000 Гц в режиме основного тона, 94,0 и 114,0 дБ относительно 20 мкПа 114,0 Основной уровень | F31: Класс 1 Погрешность показаний: ±0,5 дБ Предел допускаемой абсолютной погрешности при нормальных условиях ±0,25 дБ Предел допускаемой дополнительной погрешности, вызванной изменением температуры ±0,08 дБ Пределы отклонения уровня звукового давления при изменениях напряжения электропитания ±0,07дБ | M31: Св-во № С-АЭ/08-09-2025/ 461980384 от | Q31: № СИ015
M32: 45908 | O32: г., 12 мес.
A33: 15 | B33: Динамометр электронный АЦД/1У-0,5/1И-1 | D33: от 0,05 до 0,5кН | F33: Погрешность показаний ±0,24% | M33: С-во № С-АЭ/21-08-2025/ 458005861 от | Q33: № СИ016
M34: 45890 | O34: г., 12 мес.
A35: 16 | B35: Весы автомобильные подкладные ИСТОК-30-4П/10кг | D35: от 200 до 30000кг | F35: Пределы допускаемой погрешности: от 200 до 5000 вкл. кг ± 5 кг св. 5000 до 20000 вкл. кг ±10кг св. 20000 до 30000 вкл. кг ±15кг) | M35: Св-во № С-АЭ/05-09-2025/ 461489581 от | Q35: № СИ018
M36: 45905 | O36: г., 12 мес.
A37: 17 | B37: Весы неавтоматического действия МП150 ВДА Ф-3 | D37: от 0,04 кг до 150 кг | F37: Класс 3 Допустимое отклонение: 0,01 кг | M37: Св-во № С-АЭ/14-01-2026/ 494028488 от | Q37: № СИ019
M38: 46036 | O38: г., 12 мес.
A39: 18 | B39: Угломер с нониусом 4УМ | D39: от 0 до 180° | F39: Погрешность показаний: ± 0,10´ | M39: Св-во № С-АЭ/21-08-2025/ 458005859 от | Q39: № СИ020
M40: 45890 | O40: г., 12 мес.
A41: 19 | B41: Рейка нивелирная телескопическая Vega TS5M с уровнем 5 м | D41: от 0 до 5000мм | F41: допустимое отклонение не более: длины деления ±0,5мм, метрового интервала ±1,0мм, погрешность совмещения нуля шкалы рейки с плоскостью пятки рейки ±0,5мм, отклонение от перпендикулярности плоскости пятки рейки к продольной оси рейки 0,5мм | M41: Св-во № С-АЭ/09-07-2025/ 446008084 от | Q41: № СИ021
M42: 45847 | O42: г., 12 мес.
A43: 20 | B43: Уровень брусковый 250мм 0,02мм/м | D43: 250 мм с ценой деления 0,02 мм/м | F43: Пределы допускаемой погрешности ±0,006 мм/м | M43: Св-во № С-АЭ/21-08-2025/ 458005860 от | Q43: № СИ022
M44: 45890 | O44: г., 12 мес.
A45: 21 | B45: Мультиметр цифровой CEM DT-9908 | D45: от 200 мВ до 1000 В от 2В до 700 В от 200 Ом до 20,0 Мом | F45: Погрешность показаний: ±0,5 % показ ±2 (200мВ - 200В) ±0,8 % показ ±2 (1000В) ±1,0 % показ ±3 (2В - 200В) ±1,2 % показ ±5 (700В) ±1,0 % показ ± 4 (200 Ом) ±1,0 % показ ± 2 (2кОм) ±1,2 % показ ± 2 (20кОм-2МОм) ±2,0% показ ±5 (20МОм) | M45: Св-во № С-АЭ/09-07-2025/ 446021695 от | Q45: № СИ027
M46: 45847 | O46: г., 12 мес.
A47: 22 | B47: Течеискатель-сигнализатор «ФП-12» | D47: Порог чувствительности в режиме течеискания, объемная доля в %, по метану (CH4) 0,001; по пропану (C3H8) 0,003 Порог срабатывания сигнализации, объемная доля в %, по метану (CH4) 1,0, по пропану (C3H8) 0,4 | F47: Пределы основной абсолютной погрешности, объемная доля в %, по метану ± 0,40; по пропану ± 0,16 | M47: Св-во № С-АЭ/03-12-2025/ 486235847 от | Q47: № СИ028
M48: 45994 | O48: г., 12 мес.
A49: 23 | B49: Секундомер электронный VA-SW01 | D49: от 0,01 с до 29 мин 59,99 с | F49: Погрешность ±(10-5 ·Тх + 0,05+емр) | M49: Св-во № № С-АЭ/02-06-2025/ 436547221 от | Q49: № СИ029
M50: 45810 | O50: г., 12 мес.
A51: 24 | B51: Мультиметр Omix D4-M3-1 | D51: ~0…500 В 45...65 Гц | F51: Погрешность показаний: ±(0,5% + 1 е.м.р.) | M51: Св-во № С-АЭ/31-10-2024/ 383811488 от | Q51: № СИ031
M52: 45596 | O52: г., 48 мес.
A53: 25 | B53: Мультиметр Omix D4-M6-3 | D53: ~0…500 В 50...60 Гц | F53: Погрешность показаний: ±0,5% ±0,1Гц | M53: Св-во № С-АЭ/31-10-2024/ 383811487 от | Q53: № СИ032
M54: 45596 | O54: г., 72 мес.
A55: 26 | B55: Дальномер лазерный RGK DL50 | D55: от 0,05 м до 50 м | F55: Погрешность показаний: ±2,0 мм | M55: Св-во № С-ГСХ/04-06-2025/ 437844704 от | Q55: № СИ033
M56: 45812 | O56: г., 12 мес.
A57: 27 | B57: Плита поверочная чугунная 250*250 | D57: Размер 250x250 | F57: Класс точности 1 | M57: Св-во № С-АЭ/21-08-2025/ 458005863 от | Q57: № СИ034
M58: 45890 | O58: г., 12 мес.
A59: 28 | B59: Рулетка измерительная металлическая RGK R-5 | D59: от 0 до 5 м | F59: Класс 2 Допускаемое отклонение: мм±0,15, см±0,20, дц±0,30, м ±[0,30+0,15(L-l)] | M59: Св-во № С-АЭ/06-11-2025/ 478618345 от | Q59: № СИ035
M60: 45967 | O60: г., 12 мес.
A61: 29 | B61: Угломер с нониусом Micron, модификация УНЛ-360 | D61: от 0° до 90°х4 | F61: Пределы допускаемой абсолютной погрешности измерений: ± 5,0’ | M61: Св-во № С-АКЗ/05-09-2025/ 461700595 от | Q61: № СИ036
M62: 45905 | O62: г., 12 мес.
A63: 30 | B63: Манометр ФТ МП3-Уф 0-1 МПа в составе прибора М-100-02 (ВО080) | D63: от 0 МПа до 1 Мпа | F63: Класс точности: 1,5 Погрешность: 1,5% | M63: Св-во № С-ГГИ/10-07-2025/ 446631972 от | Q63: № СИ037
M64: 45848 | O64: г., 24 мес.
A65: 31 | B65: Линейка измерительная металлическая ГОСТ 427-75 300ꝺ | D65: от 0 мм до 300 мм | F65: Погрешность показаний: ± 0,10 мм | M65: Св-во № С-ЕПГ/07-07-2025/ 477252365 от | Q65: № СИ038
M66: 45845 | O66: г., 12 мес.
A67: 32 | B67: Линейка измерительная металлическая ГОСТ 427-75 1000ꝺ | D67: от 0 мм до 1000 мм | F67: Погрешность показаний: - до 300 мм: ± 0,10 мм - св. 300 мм до 500 мм: ± 0,15 мм - св. 500 мм до 1000 мм: ± 0,20 мм | M67: Св-во № С-ВДЧ/10-06-2025/ 439898933 от | Q67: № СИ039
M68: 45818 | O68: г., 12 мес.
A69: 33 | B69: Линейка измерительная металлическая ГОСТ 427-75 500ꝺ | D69: от 0 мм до 500 мм | F69: Погрешность показаний: - до 300 мм: ± 0,10 мм - св. 300 мм до 500 мм: ± 0,15 мм | M69: Св-во № С-ЕПГ/12-12-2025/ 489043564 от | Q69: № СИ040
M70: 46003 | O70: г., 12 мес.
A71: Испытательное оборудование
A72: № п/п | B72: Наименование испытательного оборудования | E72: Технические характеристики ИО | M72: Сведения о результатах аттестации ИО (дата, срок действия) | Q72: Заводской или инвентарный номер
A73: 34 | B73: Шар испытательный неметаллический D 100 мм ТД-056.100 | E73: Диаметр – 100±3 мм | M73: Протокол № 856/A/317 от | Q73: № ИО001
M74: 45560 | O74: г., 24 мес.
A75: 35 | B75: Шар испытательный неметаллический D 165 мм ТД-056.165 | E75: Диаметр – 165±5 мм | M75: Протокол № 855/A/317 от | Q75: № ИО002
M76: 45560 | O76: г., 24 мес.
A77: 36 | B77: Приспособление для проверки углов видимости государственного регистрационного знака ТД-139.1 | E77: Угол боковых стенок – (120+2)° Угол верхней стенки – (105+2)° Угол нижней стенки – (90+2)° Длина – (800±5) мм Ширина у основания – (182±2) мм Высота – (235±2) мм | M77: Протокол № 851/A/317 от | Q77: № ИО003
M78: 45560 | O78: г., 24 мес.
A79: 37 | B79: Приспособление для проверки углов видимости государственного регистрационного знака (квадрат)ТД-139.2 | M79: Протокол № 849/A/317 от | Q79: № ИО004
E80: Угол боковых стенок – (120+2)° Угол верхней стенки – (105+2)° Угол нижней стенки – (90+2)° Длина – (574±2) мм Ширина у основания – (170±2) мм Высота – (235±2) мм | M80: 45560 | O80: г., 24 мес.
A81: 38 | B81: Радиусный шаблон 3,2мм | E81: Номинальный рабочий радиус, мм 3,2 | M81: Протокол № 699/А/317 от | Q81: № ИО006
M82: 45519 | O82: г., 24 мес.
A83: 39 | B83: Опорная поверхность ОП-1 | E83: Ширина площадки: 4,50м Длина площадки: 8,15м Отклонение от горизонтали опорной поверхности: ±5´ Отклонение от плоскостности опорной поверхности: ±1мм | M83: Протокол № 26/300 от | Q83: № ИО007
M84: 46118 | O84: г., 12 мес.
A85: 40 | B85: Набор радиусных шаблонов Vogel 1-7 мм | E85: Номинальный рабочий радиус, мм 1; 1,25; 1.5; 1,75; 2; 2,25; 2,5; 2,75; 3; 3,5; 4; 4,5; 5; 5,5;6; 6,5; 7 | M85: Протокол № 25060501ПА от | Q85: № ИО008
M86: 45783 | O86: г., 12 мес.
A87: 41 | B87: Опорная поверхность ОП-2 | E87: Ширина площадки: 3900 мм Длина площадки: 6880 мм Отклонение от плоскости горизонта опорной поверхности: ±2° Отклонение от плоскостности опорной поверхности: ±3мм | M87: Протокол № 25/375 от | Q87: № ИО009
M88: 45902 | O88: г., 12 мес.
A89: Вспомогательное оборудование
A90: № п/п | B90: Наименование вспомогательного оборудования | E90: Назначение | Q90: Заводской или инвентарный номер
A91: 44 | B91: Уровень строительный УС-1-2000 | E91: Предназначен для регулировки уровня поверхностей ТС при измерении их габаритных размеров | Q91: №ВО001
A92: 45 | B92: Диагностический мультимарочный сканер Launch CRP919 MAX LNC-190 | E92: Предназначен для диагностики ТС | Q92: № ВО002
A93: 46 | B93: Отвес строительный USP – 5м, 100гр | E93: Предназначен для точного определения или проверки вертикальной плоскости или линии | Q93: № ВО003
A94: 47 | B94: Отвес конусный – 5м, 200гр | E94: Предназначен для точного определения или проверки вертикальной плоскости или линии | Q94: № ВО004
A95: 48 | B95: Отвес строительный Зубр – 5м, 500гр | E95: Предназначен для точного определения или проверки вертикальной плоскости или линии | Q95: № ВО005
A96: 49 | B96: Тестер проверки люфтов в деталях рулевого управления RT-4000PD | E96: Предназначен для диагностики шаровых опор подвески, шарниров рулевых тяг, сайлентблоков, втулок стабилизатора, подшипников ступиц | Q96: № ВО006
A97: 50 | B97: Набор инструментов Stels 82 предмета | E97: Разборочно-сборочные работы при диагностике ТС | Q97: № ВО007
A98: 51 | B98: Автомобильный компрессор Агрессор AGR160 | E98: Предназначен для накачивания различных надувных изделий, измерения давления | Q98: №ВО008
A99: 52 | B99: Прибор проверки герметичности пневматического тормозного привода автотранспортных средств М-100-02 | E99: Предназначен для проверки герметичности пневматического тормозного привода | Q99: №ВО009
A100: 53 | B100: Домкрат подкатной 3т | E100: Предназначен для подъема опирающегося на него груза | Q100: №ВО010
...

Sheet Лист оценки
B1: Лист оценки неопределенности к протоколу № АТ04 от 12.09.2025 г.
B2: Методика | C2: Определяемая характеристика | D2: Единицы измерения | E2: Используемое оборудование | G2: Количество контрольных процедур (измерений) | H2: Результаты измерений: Х1 – если одно измерение, Хn если несколько измерений | I2: Расчет неопределенности
E3: Наименование оборудования, зав./инв. № | F3: Погрешность (применимая для расчета неопределённости) | H3: X1 | I3: Неопределенность по типу А, UA | J3: Неопределенность по типу B, UB | K3: Суммарная стандартная неопределенность, uc | L3: Расширенная неопределенность (при Р=95%, k=1,65 u | M3: Примечание
B4: п.А.1.2.2 Приложения А, ГОСТ 33670-2015 | C4: Угол между плоскостью переднего государственного регистрационного знака и продольной плоскостью симметрии ТС | D4: Градусы, ° | E4: Угломер с нониусом Micron, модификация УНЛ-360 Зав. № 4-24020385 Инв. № СИ036 | F4: ± 5' | G4: 1 | H4: =Расчет!O55 -> 90 | I4: 0 | J4: =Расчет!D30 -> 0.048112522 | K4: =Расчет!F40 -> 0.048112522 | L4: =Расчет!Q55 -> 0.079385662
B5: п.А.1.2.2 Приложения А, ГОСТ 33670-2015 | C5: Угол между плоскостью заднего государственного регистрационного знака и продольной плоскостью симметрии ТС | D5: Градусы, ° | E5: Угломер с нониусом Micron, модификация УНЛ-360 Зав. № 4-24020385 Инв. № СИ036 | F5: ± 5' | G5: 1 | H5: =Расчет!O56 -> 90 | I5: 0 | J5: =Расчет!D30 -> 0.048112522 | K5: =Расчет!F46 -> 0.048112522 | L5: =Расчет!Q56 -> 0.079385662
B6: п.А.1.2.2 Приложения А, ГОСТ 33670-2015 | C6: Угол между плоскостью переднего государственного регистрационного знака и опорной поверхностью | D6: Градусы, ° | E6: Угломер маятниковый З УРИ-М Зав. № 9405 Инв. № СИ009 | F6: ±1° | G6: 1 | H6: =Расчет!N95 -> 90 | I6: 0 | J6: =Расчет!D68 -> 0.57735027 | K6: =Расчет!F81 -> 0.57735027 | L6: =Расчет!P95 -> 0.95262794
B7: п.А.1.2.2 Приложения А, ГОСТ 33670-2015 | C7: Угол между плоскостью заднего государственного регистрационного знака и опорной поверхностью | D7: Градусы, ° | E7: Угломер маятниковый З УРИ-М Зав. № 9405 Инв. № СИ009 | F7: ±1° | G7: 1 | H7: =Расчет!N96 -> 90 | I7: 0 | J7: =Расчет!D68 -> 0.57735027 | K7: =Расчет!F87 -> 0.57735027 | L7: =Расчет!P96 -> 0.95262794
B8: п.А.1.2.2, п.А.1.2.3 Приложения А, ГОСТ 33670-2015 | C8: Высота от опорной плоскости верхнего края переднего государственного регистрационного знака | D8: миллиметры, мм | E8: Рулетка RGK R-5 Зав. № 2438 Инв. № СИ035 | F8: ±0,3 мм | G8: 1 | H8: =Расчет!N166 -> 302 | I8: 0 | J8: =Расчет!E116 -> 0.11547005 | K8: =Расчет!C123 -> 0.17320508 | L8: =Расчет!P166 -> 0.28578838
B9: п.А.1.2.2, п.А.1.2.3 Приложения А, ГОСТ 33670-2015 | C9: Высота от опорной плоскости верхнего края заднего государственного регистрационного знака | D9: миллиметры, мм | E9: Рулетка RGK R-5 Зав. № 2438 Инв. № СИ035 | F9: ±0,3 мм | G9: 1 | H9: =Расчет!N167 -> 600 | I9: 0 | J9: =Расчет!E116 -> 0.11547005 | K9: =Расчет!C125 -> 0.17320508 | L9: =Расчет!P167 -> 0.28578838
B10: п.А.1.2.3 Приложения А, ГОСТ 33670-2015 | C10: Высота от опорной плоскости нижнего края переднего государственного регистрационного знака | D10: миллиметры, мм | E10: Рулетка RGK R-5 Зав. № 2438 Инв. № СИ035 | F10: ±0,3 мм | G10: 1 | H10: =Расчет!N168 -> 500 | I10: 0 | J10: =Расчет!E116 -> 0.11547005 | K10: =Расчет!C127 -> 0.17320508 | L10: =Расчет!P168 -> 0.28578838
B11: п.А.1.2.3 Приложения А, ГОСТ 33670-2015 | C11: Высота от опорной плоскости нижнего края заднего государственного регистрационного знака | D11: миллиметры, мм | E11: Рулетка RGK R-5 Зав. № 2438 Инв. № СИ035 | F11: ±0,3 мм | G11: 1 | H11: =Расчет!N169 -> 500 | I11: 0 | J11: =Расчет!E116 -> 0.11547005 | K11: =Расчет!C129 -> 0.17320508 | L11: =Расчет!P169 -> 0.28578838
B12: п.А.5.1.1.3 Приложения А, ГОСТ 33670-2015 | C12: Усилие на органе управления рабочей тормозной системы 1 Оси | D12: Ньютон, Н | E12: Стенд тормозной СТН 13000.01 Зав. № 507 Инв. № СИ006 | F12: Относительная ± 5% | G12: 1 | H12: =Расчет!L266 -> 490 | I12: 0 | J12: =Расчет!E217 -> 14.148027 | K12: =Расчет!F241 -> 14.148027 | L12: =Расчет!N266 -> 23.344244
B13: п.А.5.1.1.3 Приложения А, ГОСТ 33670-2015 | C13: Усилие на органе управления рабочей тормозной системы 2 Оси | D13: Ньютон, Н | E13: Стенд тормозной СТН 13000.01 Зав. № 507 Инв. № СИ006 | F13: Относительная ± 5% | G13: 1 | H13: =Расчет!L267 -> 490 | I13: 0 | J13: =Расчет!E224 -> 14.148027 | K13: =Расчет!F247 -> 14.148027 | L13: =Расчет!N267 -> 23.344244
B14: п.А.5.1.5 Приложения А, ГОСТ 33670-2015 | C14: Усилие на органе управления стояночной тормозной системы | D14: Ньютон, Н | E14: Стенд тормозной СТН 13000.01 Зав. № 507 Инв. № СИ006 | F14: Относительная ± 5% | G14: 1 | H14: =Расчет!L268 -> 490 | I14: 0 | J14: =Расчет!E231 -> 14.148027 | K14: =Расчет!F253 -> 14.148027 | L14: =Расчет!N268 -> 23.344244
B15: п.А.5.1.1.4, А.5.9 Приложения А, ГОСТ 33670-2015 | C15: Относительная разности тормозных сил колес 1 оси | D15: Проценты, % | E15: Стенд тормозной СТН 13000.01 Зав. № 507 Инв. № СИ006 | F15: Относительная ± 3% | G15: 1 | H15: =Расчет!I545 -> 0 | I15: 0 | J15: - | K15: =Расчет!F530 -> 2.4582579 | L15: =Расчет!K545 -> 4.0561256
B16: п.А.5.1.1.4, А.5.9 Приложения А, ГОСТ 33670-2015 | C16: Относительная разности тормозных сил колес 2 оси | D16: Проценты, % | E16: Стенд тормозной СТН 13000.01 Зав. № 507 Инв. № СИ006 | F16: Относительная ± 3% | G16: 1 | H16: =Расчет!I546 -> 15 | I16: 0 | J16: - | K16: =Расчет!F536 -> 3.0092933 | L16: =Расчет!K546 -> 4.965334
B17: п.А.5.1.1.3, п.А.5.9 Приложения А, ГОСТ 33670-2015 | C17: Удельная тормозная сила рабочей тормозной системы | D17: Безразмерная величина | E17: Стенд тормозной СТН 13000.01 Зав. № 507 Инв. № СИ006 | F17: Относительная ± 3% | G17: 1 | H17: =Расчет!J443 -> 0.55527902 | I17: 0 | J17: - | K17: =Расчет!F420 -> 0.010776185 | L17: =Расчет!L443 -> 0.017780705
B18: п.А.5.1.4.1.1, п.А.5,9 Приложения А, ГОСТ 33670-2015 | C18: Удельная тормозная сила стояночной тормозной системы | D18: Безразмерная величина | E18: Стенд тормозной СТН 13000.01 Зав. № 507 Инв. № СИ006 | F18: Относительная ± 3% | G18: 1 | H18: =Расчет!J444 -> 0.22675737 | I18: 0 | J18: - | K18: =Расчет!F428 -> 0.0048175823 | L18: =Расчет!L444 -> 0.0079490108
B19: п.А.5 Приложения А, ГОСТ 33670-2015 | C19: Нагрузка на 1 ось | D19: Килограммы, кг | E19: Стенд тормозной СТН 13000.01 Зав. № 507 Инв. № СИ006 | F19: Относительная ± 3% | G19: 1 | H19: =Расчет!H615 -> 995 | I19: 0 | J19: =Расчет!E570 -> 17.233906 | K19: =Расчет!C581 -> 17.233906 | L19: =Расчет!J615 -> 28.435944
B20: п.А.5 Приложения А, ГОСТ 33670-2015 | C20: Нагрузка на 2 ось | D20: Килограммы, кг | E20: Стенд тормозной СТН 13000.01 Зав. № 507 Инв. № СИ006 | F20: Относительная ± 3% | G20: 1 | H20: =Расчет!H616 -> 850 | I20: 0 | J20: =Расчет!E576 -> 14.722432 | K20: =Расчет!C583 -> 14.722432 | L20: =Расчет!J616 -> 24.292013
B21: п.А.8.9 Приложения А, ГОСТ 33670-2015 | C21: Высота нижней границы размещения левой фары ближнего света над опорной поверхностью | D21: миллиметры, мм | E21: Рулетка RGK R-5 Зав. № 2438 Инв. № СИ035 | F21: ±0,3 мм | G21: 1 | H21: =Расчет!O908 -> 630 | I21: 0 | J21: =Расчет!E665 -> 0.17320508 | K21: =Расчет!C672 -> 0.17320508 | L21: =Расчет!Q908 -> 0.28578838
B22: п.А.8.9 Приложения А, ГОСТ 33670-2015 | C22: Высота нижней границы размещения правой фары ближнего света над опорной поверхностью | D22: миллиметры, мм | E22: Рулетка RGK R-5 Зав. № 2438 Инв. № СИ035 | F22: ±0,3 мм | G22: 1 | H22: =Расчет!O909 -> 630 | I22: 0 | J22: =Расчет!E665 -> 0.17320508 | K22: =Расчет!C674 -> 0.17320508 | L22: =Расчет!Q909 -> 0.28578838
B23: п.А.8.9 Приложения А, ГОСТ 33670-2015 | C23: Высота верхней границы размещения левой фары ближнего света над опорной поверхностью | D23: миллиметры, мм | E23: Рулетка RGK R-5 Зав. № 2438 Инв. № СИ035 | F23: ±0,3 мм | G23: 1 | H23: =Расчет!O910 -> 780 | I23: 0 | J23: =Расчет!E665 -> 0.17320508 | K23: =Расчет!C676 -> 0.17320508 | L23: =Расчет!Q910 -> 0.28578838
B24: п.А.8.9 Приложения А, ГОСТ 33670-2015 | C24: Высота верхней границы размещения правой фары ближнего света над опорной поверхностью | D24: миллиметры, мм | E24: Рулетка RGK R-5 Зав. № 2438 Инв. № СИ035 | F24: ±0,3 мм | G24: 1 | H24: =Расчет!O911 -> 780 | I24: 0 | J24: =Расчет!E665 -> 0.17320508 | K24: =Расчет!C678 -> 0.17320508 | L24: =Расчет!Q911 -> 0.28578838
B25: п. А.8.10.1 Приложения А ГОСТ 33670-2015 | C25: Точка видимой поверхности в направлении исходной оси, которая в наибольшей степени удалена от средней продольной плоскости ТС от края габаритной ширины ТС передней левой противотуманной фары | D25: миллиметры, мм | E25: Рулетка RGK R-5 Зав. № 2438 Инв. № СИ035 | F25: ±0,3 мм | G25: 1 | H25: =Расчет!O912 -> 100 | I25: 0 | J25: =Расчет!E665 -> 0.17320508 | K25: =Расчет!C680 -> 0.17320508 | L25: =Расчет!Q912 -> 0.28578838 | N25: Наличие отсутствие противотуманок передних
B26: п. А.8.10.1 Приложения А ГОСТ 33670-2015 | C26: Точка видимой поверхности в направлении исходной оси, которая в наибольшей степени удалена от средней продольной плоскости ТС от края габаритной ширины ТС передней правой противотуманной фары | D26: миллиметры, мм | E26: Рулетка RGK R-5 Зав. № 2438 Инв. № СИ035 | F26: ±0,3 мм | G26: 1 | H26: =Расчет!O913 -> 100 | I26: 0 | J26: =Расчет!E665 -> 0.17320508 | K26: =Расчет!C682 -> 0.17320508 | L26: =Расчет!Q913 -> 0.28578838
B27: п. А.8.10.2 Приложения А ГОСТ 33670-2015 | C27: Расстояние от нижней точки левой передней противотуманной фары до опорной поверхности | D27: миллиметры, мм | E27: Рулетка RGK R-5 Зав. № 2438 Инв. № СИ035 | F27: ±0,3 мм | G27: 1 | H27: =Расчет!O914 -> 260 | I27: 0 | J27: =Расчет!E665 -> 0.17320508 | K27: =Расчет!C684 -> 0.17320508 | L27: =Расчет!Q914 -> 0.28578838
B28: п. А.8.10.2 Приложения А ГОСТ 33670-2015 | C28: Расстояние от нижней точки правой передней противотуманной фары до опорной поверхности | D28: миллиметры, мм | E28: Рулетка RGK R-5 Зав. № 2438 Инв. № СИ035 | F28: ±0,3 мм | G28: 1 | H28: =Расчет!O915 -> 260 | I28: 0 | J28: =Расчет!E665 -> 0.17320508 | K28: =Расчет!C686 -> 0.17320508 | L28: =Расчет!Q915 -> 0.28578838
B29: п. А.8.10.2 Приложения А ГОСТ 33670-2015 | C29: Расстояние от верхней точки левой передней противотуманной фары до опорной поверхности | D29: миллиметры, мм | E29: Рулетка RGK R-5 Зав. № 2438 Инв. № СИ035 | F29: ±0,3 мм | G29: 1 | H29: =Расчет!O916 -> 280 | I29: 0 | J29: =Расчет!E665 -> 0.17320508 | K29: =Расчет!C688 -> 0.17320508 | L29: =Расчет!Q916 -> 0.28578838
B30: п. А.8.10.2 Приложения А ГОСТ 33670-2015 | C30: Расстояние от верхней точки правой передней противотуманной фары до опорной поверхности | D30: миллиметры, мм | E30: Рулетка RGK R-5 Зав. № 2438 Инв. № СИ035 | F30: ±0,3 мм | G30: 1 | H30: =Расчет!O917 -> 280 | I30: 0 | J30: =Расчет!E665 -> 0.17320508 | K30: =Расчет!C690 -> 0.17320508 | L30: =Расчет!Q917 -> 0.28578838
B31: п.А.8.12.1 Приложения А, ГОСТ 33670-2015 | C31: Расстояние от точки видимой поверхности левого сигнала торможения в направлении исходной оси, которая в наибольшей степени удалена от средней продольной плоскости ТС до края габаритной ширины ТС | D31: миллиметры, мм | E31: Рулетка RGK R-5 Зав. № 2438 Инв. № СИ035 | F31: ±0,3 мм | G31: 1 | H31: =Расчет!O918 -> 150 | I31: 0 | J31: =Расчет!E665 -> 0.17320508 | K31: =J31 -> 0.17320508 | L31: =Расчет!Q918 -> 0.28578838
B32: п.А.8.12.1 Приложения А, ГОСТ 33670-2015 | C32: Расстояние от точки видимой поверхности правого сигнала торможения в направлении исходной оси, которая в наибольшей степени удалена от средней продольной плоскости ТС до края габаритной ширины ТС | D32: миллиметры, мм | E32: Рулетка RGK R-5 Зав. № 2438 Инв. № СИ035 | F32: ±0,3 мм | G32: 1 | H32: =Расчет!O919 -> 150 | I32: 0 | J32: =Расчет!E665 -> 0.17320508 | K32: =J32 -> 0.17320508 | L32: =Расчет!Q919 -> 0.28578838
B33: п.А.8.12.2 Приложения А, ГОСТ 33670-2015 | C33: Расстояние от нижней точки левого сигнала торможения на кузове до опорной поверхности | D33: миллиметры, мм | E33: Рулетка RGK R-5 Зав. № 2438 Инв. № СИ035 | F33: ±0,3 мм | G33: 1 | H33: =Расчет!O920 -> 890 | I33: 0 | J33: =Расчет!E665 -> 0.17320508 | K33: =J33 -> 0.17320508 | L33: =Расчет!Q920 -> 0.28578838 | N33: На каких то машинах только кузов, а где то и багажник и кузов
B34: п.А.8.12.2 Приложения А, ГОСТ 33670-2015 | C34: Расстояние от нижней точки правого сигнала торможения на кузове до опорной поверхности | D34: миллиметры, мм | E34: Рулетка RGK R-5 Зав. № 2438 Инв. № СИ035 | F34: ±0,3 мм | G34: 1 | H34: =Расчет!O921 -> 890 | I34: 0 | J34: =Расчет!E665 -> 0.17320508 | K34: =J34 -> 0.17320508 | L34: =Расчет!Q921 -> 0.28578838
B35: п.А.8.12.2 Приложения А, ГОСТ 33670-2015 | C35: Расстояние от верхней точки левого сигнала торможения на кузове до опорной поверхности | D35: миллиметры, мм | E35: Рулетка RGK R-5 Зав. № 2438 Инв. № СИ035 | F35: ±0,3 мм | G35: 1 | H35: =Расчет!O922 -> 955 | I35: 0 | J35: =Расчет!E665 -> 0.17320508 | K35: =J35 -> 0.17320508 | L35: =Расчет!Q922 -> 0.28578838
B36: п.А.8.12.2 Приложения А, ГОСТ 33670-2015 | C36: Расстояние от верхней точки правого сигнала торможения на кузове до опорной поверхности | D36: миллиметры, мм | E36: Рулетка RGK R-5 Зав. № 2438 Инв. № СИ035 | F36: ±0,3 мм | G36: 1 | H36: =Расчет!O923 -> 955 | I36: 0 | J36: =Расчет!E665 -> 0.17320508 | K36: =J36 -> 0.17320508 | L36: =Расчет!Q923 -> 0.28578838
B37: п.А.8.12.2 Приложения А, ГОСТ 33670-2015 | C37: Расстояние от нижней точки левого сигнала торможения на крышке багажника до опорной поверхности | D37: миллиметры, мм | E37: Рулетка RGK R-5 Зав. № 2438 Инв. № СИ035 | F37: ±0,3 мм | G37: 1 | H37: =Расчет!O924 -> 860 | I37: 0 | J37: =Расчет!E665 -> 0.17320508 | K37: =J37 -> 0.17320508 | L37: =Расчет!Q924 -> 0.28578838
B38: п.А.8.12.2 Приложения А, ГОСТ 33670-2015 | C38: Расстояние от нижней точки правого сигнала торможения на крышке багажника до опорной поверхности | D38: миллиметры, мм | E38: Рулетка RGK R-5 Зав. № 2438 Инв. № СИ035 | F38: ±0,3 мм | G38: 1 | H38: =Расчет!O925 -> 865 | I38: 0 | J38: =Расчет!E665 -> 0.17320508 | K38: =J38 -> 0.17320508 | L38: =Расчет!Q925 -> 0.28578838
B39: п.А.8.12.2 Приложения А, ГОСТ 33670-2015 | C39: Расстояние от верхней точки левого сигнала торможения на крышке багажника до опорной поверхности | D39: миллиметры, мм | E39: Рулетка RGK R-5 Зав. № 2438 Инв. № СИ035 | F39: ±0,3 мм | G39: 1 | H39: =Расчет!O926 -> 935 | I39: 0 | J39: =Расчет!E665 -> 0.17320508 | K39: =J39 -> 0.17320508 | L39: =Расчет!Q926 -> 0.28578838
B40: п.А.8.12.2 Приложения А, ГОСТ 33670-2015 | C40: Расстояние от верхней точки правого сигнала торможения на крышке багажника до опорной поверхности | D40: миллиметры, мм | E40: Рулетка RGK R-5 Зав. № 2438 Инв. № СИ035 | F40: ±0,3 мм | G40: 1 | H40: =Расчет!O927 -> 940 | I40: 0 | J40: =Расчет!E665 -> 0.17320508 | K40: =J40 -> 0.17320508 | L40: =Расчет!Q927 -> 0.28578838
B41: п.А.8.12.3 Приложения А, ГОСТ 33670-2015 | C41: Расстояние от дополнительного сигнала торможения до опорной поверхности | D41: миллиметры, мм | E41: Рулетка RGK R-5 Зав. № 2438 Инв. № СИ035 | F41: ±(0,30+0,15(L-1)) мм | G41: 1 | H41: =Расчет!O928 -> 1140 | I41: 0 | J41: =Расчет!E665 -> 0.17320508 | K41: =J41 -> 0.17320508 | L41: =Расчет!Q928 -> 0.28578838
B42: п.А.8.12.3 Приложения А, ГОСТ 33670-2015 | C42: Расстояние от дополнительного сигнала торможения до нижнего края внешней поверхности или покрытия заднего стекла | D42: миллиметры, мм | E42: Рулетка RGK R-5 Зав. № 2438 Инв. № СИ035 | F42: ±0,15 мм | G42: 1 | H42: =Расчет!O929 -> 5 | I42: 0 | J42: =Расчет!E657 -> 0.08660254 | K42: =J42 -> 0.08660254 | L42: =Расчет!Q929 -> 0.14289419
B43: п.А.8.12.4 Приложения А, ГОСТ 33670-2015 | C43: Смещение оптического центра дополнительного сигнала торможения влево или вправо от оси симетрии транспортного средства | D43: миллиметры, мм | E43: Рулетка RGK R-5 Зав. № 2438 Инв. № СИ035 | F43: ±0,2 мм | G43: 1 | H43: =Расчет!O930 -> 0 | I43: 0 | J43: =Расчет!E657 -> 0.08660254 | K43: =J43 -> 0.08660254 | L43: =Расчет!Q930 -> 0.14289419
B44: п.А.8.13.2 Приложения А, ГОСТ 33670-2015 | C44: Расстояние от нижней точки задних левых противотуманных фар до опорной поверхности | D44: миллиметры, мм | E44: Рулетка RGK R-5 Зав. № 2438 Инв. № СИ035 | F44: ±0,3 мм | G44: 1 | H44: =Расчет!O931 -> 850 | I44: 0 | J44: =Расчет!E665 -> 0.17320508 | K44: =J44 -> 0.17320508 | L44: =Расчет!Q931 -> 0.28578838 | N44: Задние противотуманки могут быть 1 или 2
B45: п.А.8.13.2 Приложения А, ГОСТ 33670-2015 | C45: Расстояние от нижней точки задних правых противотуманных фонарей до опорной поверхности | D45: миллиметры, мм | E45: Рулетка RGK R-5 Зав. № 2438 Инв. № СИ035 | F45: ±0,3 мм | G45: 1 | H45: =Расчет!O932 -> 850 | I45: 0 | J45: =Расчет!E665 -> 0.17320508 | K45: =J45 -> 0.17320508 | L45: =Расчет!Q932 -> 0.28578838
B46: п.А.8.13.2 Приложения А, ГОСТ 33670-2015 | C46: Расстояние от верхней точки задних левых противотуманных фар до опорной поверхности | D46: миллиметры, мм | E46: Рулетка RGK R-5 Зав. № 2438 Инв. № СИ035 | F46: ±0,3 мм | G46: 1 | H46: =Расчет!O933 -> 940 | I46: 0 | J46: =Расчет!E665 -> 0.17320508 | K46: =J46 -> 0.17320508 | L46: =Расчет!Q933 -> 0.28578838
B47: п.А.8.13.2 Приложения А, ГОСТ 33670-2015 | C47: Расстояние от верхней точки задних правых противотуманных фонарей до опорной поверхности | D47: миллиметры, мм | E47: Рулетка RGK R-5 Зав. № 2438 Инв. № СИ035 | F47: ±0,3 мм | G47: 1 | H47: =Расчет!O934 -> 940 | I47: 0 | J47: =Расчет!E665 -> 0.17320508 | K47: =J47 -> 0.17320508 | L47: =Расчет!Q934 -> 0.28578838
B48: п.А.8.20.6 Приложения А, ГОСТ 33670-2015 | C48: Сила света левой фары в направлении 34' вверх от положения левой части светодиодной границы | D48: Канделы, кд | E48: Измеритель параметров света фар автотранспортных средств ИПФ-01 Зав. № 9843 Инв. № СИ001 | F48: ± 15% | G48: 1 | H48: =Расчет!N1039 -> 643 | I48: 0 | J48: =Расчет!E971 -> 55.685441 | K48: =J48 -> 55.685441 | L48: =Расчет!P1039 -> 91.880978
B49: п.А.8.20.6 Приложения А, ГОСТ 33670-2015 | C49: Сила света правой фары в направлении 34' вверх от положения левой части светодиодной границы | D49: Канделы, кд | E49: Измеритель параметров света фар автотранспортных средств ИПФ-01 Зав. № 9843 Инв. № СИ001 | F49: ± 15% | G49: 1 | H49: =Расчет!N1040 -> 470 | I49: 0 | J49: =Расчет!E978 -> 40.703204 | K49: =J49 -> 40.703204 | L49: =Расчет!P1040 -> 67.160287
B50: п.А.8.20.6 Приложения А, ГОСТ 33670-2015 | C50: Сила света левой фары в направлении 52' вниз от положения левой части светодиодной границы | D50: Канделы, кд | E50: Измеритель параметров света фар автотранспортных средств ИПФ-01 Зав. № 9843 Инв. № СИ001 | F50: ± 15% | G50: 1 | H50: =Расчет!N1041 -> 1600 | I50: 0 | J50: =Расчет!E986 -> 138.56407 | K50: =J50 -> 138.56407 | L50: =Расчет!P1041 -> 228.63071
B51: п.А.8.20.6 Приложения А, ГОСТ 33670-2015 | C51: Сила света правой фары в направлении 52' вниз от положения левой части светодиодной границы | D51: Канделы, кд | E51: Измеритель параметров света фар автотранспортных средств ИПФ-01 Зав. № 9843 Инв. № СИ001 | F51: ± 15% | G51: 1 | H51: =Расчет!N1042 -> 3800 | I51: 0 | J51: =Расчет!E994 -> 329.08965 | K51: =J51 -> 329.08965 | L51: =Расчет!P1042 -> 542.99793
B52: п.А.8.20.7 Приложения А, ГОСТ 33670-2015 | C52: Максимальная сила света левой фары в режиме "Дальний свет" | D52: Канделы, кд | E52: Измеритель параметров света фар автотранспортных средств ИПФ-01 Зав. № 9843 Инв. № СИ001 | F52: ± 15% | G52: 1 | H52: =Расчет!K947 -> 125000 | I52: 0 | J52: =Расчет!C1076 -> 10825.318 | K52: =J52 -> 10825.318 | L52: -
B53: п.А.8.20.7 Приложения А, ГОСТ 33670-2015 | C53: Максимальная сила света правой фары в режиме "Дальний свет" | D53: Канделы, кд | E53: Измеритель параметров света фар автотранспортных средств ИПФ-01 Зав. № 9843 Инв. № СИ001 | F53: ± 15% | G53: 1 | H53: =Расчет!M947 -> 125000 | I53: 0 | J53: =Расчет!C1084 -> 10825.318 | K53: =J53 -> 10825.318 | L53: -
B54: п.А.8.20.7 Приложения А, ГОСТ 33670-2015 | C54: Максимальная сила света всех фар в режиме "Дальний свет" | D54: Канделы, кд | E54: Измеритель параметров света фар автотранспортных средств ИПФ-01 Зав. № 9843 Инв. № СИ001 | F54: ± 15% | G54: 1 | H54: =Расчет!K949 -> 250000 | I54: 0 | J54: - | K54: =Расчет!F1097 -> 15309.311 | L54: =Расчет!O1112 -> 25260.363
B55: п.А.8.22.1 Приложения А, ГОСТ 33670-2015 | C55: Частота следования проблесков указателей поворота | D55: Герц, Гц | E55: Измеритель параметров света фар автотранспортных средств ИПФ-01 Зав. № 9843 Инв. № СИ001 | F55: ± 0,1 Гц | G55: 1 | H55: =Расчет!K1149 -> 1.4 | I55: 0 | J55: =Расчет!E1130 -> 0.064549722 | K55: =J55 -> 0.064549722 | L55: =Расчет!M1149 -> 0.10650704
B56: п.А.8.22.1 Приложения А, ГОСТ 33670-2015 | C56: Частота следования проблесков указателей поворота | D56: (проблесков в минуту) | E56: Измеритель параметров света фар автотранспортных средств ИПФ-01 Зав. № 9843 Инв. № СИ001 | F56: ± 0,1 Гц | G56: 1 | H56: =H55*60 -> 84 | I56: 0 | J56: =J55*60 -> 3.8729833 | K56: =J56 -> 3.8729833 | L56: =L55*60 -> 6.3904225 | N56: Нужно ли?
B57: п.А.8.22.2 Приложения А, ГОСТ 33670-2015 | C57: Частота следования проблесков аварийной сигнализации | D57: Герц, Гц | E57: Измеритель параметров света фар автотранспортных средств ИПФ-01 Зав. № 9843 Инв. № СИ001 | F57: ± 0,1 Гц | G57: 1 | H57: =H55 -> 1.4 | I57: 0 | J57: =J55 -> 0.064549722 | K57: =J57 -> 0.064549722 | L57: =Расчет!M1150 -> 0.10650704
B58: п.А.8.22.2 Приложения А, ГОСТ 33670-2015 | C58: Частота следования проблесков аварийной сигнализации | D58: (проблесков в минуту) | E58: Измеритель параметров света фар автотранспортных средств ИПФ-01 Зав. № 9843 Инв. № СИ001 | F58: ± 0,1 Гц | G58: 1 | H58: =H56 -> 84 | I58: 0 | J58: =J56 -> 3.8729833 | K58: =J58 -> 3.8729833 | L58: =L57*60 -> 6.3904225
A59: п.А.10.7.3 Приложения А, ГОСТ 33670-2015 ЕСЛИ зимние шины | B59: п.А.10.7.2 Приложения А, ГОСТ 33670-2015 | C59: Остаточная глубины рисунка протектора передней левой шины | D59: Миллиметры, мм | E59: Штангенциркуль ШЦ-I-150-0,05 Зав. № Н321080361 Инв. № СИ008 | F59: ± 0,05 мм | G59: 1 | H59: =Расчет!K1208 -> 6 | I59: 0 | J59: =Расчет!E1170 -> 0.028867513 | K59: =J59 -> 0.028867513 | L59: =Расчет!M1208 -> 0.047631397 | N59: Необходимо чтобы ссылка автоматически менялась летние или зимние шины
B60: п.А.10.7.2 Приложения А, ГОСТ 33670-2015 | C60: Остаточная глубины рисунка протектора передней правой шины | D60: Миллиметры, мм | E60: Штангенциркуль ШЦ-I-150-0,05 Зав. № Н321080361 Инв. № СИ008 | F60: ± 0,05 мм | G60: 1 | H60: =Расчет!K1209 -> 6 | I60: 0 | J60: =J59 -> 0.028867513 | K60: =K59 -> 0.028867513 | L60: =Расчет!M1209 -> 0.047631397
B61: п.А.10.7.2 Приложения А, ГОСТ 33670-2015 | C61: Остаточная глубины рисунка протектора задней левой шины | D61: Миллиметры, мм | E61: Штангенциркуль ШЦ-I-150-0,05 Зав. № Н321080361 Инв. № СИ008 | F61: ± 0,05 мм | G61: 1 | H61: =Расчет!K1210 -> 6 | I61: 0 | J61: =J60 -> 0.028867513 | K61: =K60 -> 0.028867513 | L61: =Расчет!M1210 -> 0.047631397
B62: п.А.10.7.2 Приложения А, ГОСТ 33670-2015 | C62: Остаточная глубины рисунка протектора задней правой шины | D62: Миллиметры, мм | E62: Штангенциркуль ШЦ-I-150-0,05 Зав. № Н321080361 Инв. № СИ008 | F62: ± 0,05 мм | G62: 1 | H62: =Расчет!K1211 -> 6 | I62: 0 | J62: =J61 -> 0.028867513 | K62: =K61 -> 0.028867513 | L62: =Расчет!M1211 -> 0.047631397
B63: п.А.11.8 Приложения А, ГОСТ 33670-2015 | C63: Светопропускание ветровго стекла | D63: Проценты, % | E63: Измеритель светопропускания стекол «ТОНИК» Зав. № 18861 Инв. № СИ004 | F63: ± 2 % | G63: 1 | H63: =Расчет!H1347 -> 82.3 | I63: 0 | J63: =Расчет!D1304 -> 1.1550613 | K63: =J63 -> 1.1550613 | L63: =Расчет!J1347 -> 1.9058512 | N63: Необходимо ли учитывать передние глухие форточки?!
B64: п.А.11.8 Приложения А, ГОСТ 33670-2015 | C64: Светопропускание правого стекла | D64: Проценты, % | E64: Измеритель светопропускания стекол «ТОНИК» Зав. № 18861 Инв. № СИ004 | F64: ± 2 % | G64: 1 | H64: =Расчет!H1348 -> 80.7 | I64: 0 | J64: =Расчет!D1304 -> 1.1550613 | K64: =J64 -> 1.1550613 | L64: =Расчет!J1348 -> 1.9058512
B65: п.А.11.8 Приложения А, ГОСТ 33670-2015 | C65: Светопропускание левого стекла | D65: Проценты, % | E65: Измеритель светопропускания стекол «ТОНИК» Зав. № 18861 Инв. № СИ004 | F65: ± 2 % | G65: 1 | H65: =Расчет!H1350 -> 80.9 | I65: 0 | J65: =Расчет!D1304 -> 1.1550613 | K65: =J65 -> 1.1550613 | L65: =Расчет!J1350 -> 1.9058512
B66: п.А.11.8 Приложения А, ГОСТ 33670-2015 | C66: Ширина светозащитной полосы | D66: Миллиметры, мм | E66: Рулетка RGK R-5 Зав.№ 2438 Инв. № СИ035 | F66: ± 0,2 мм | G66: 1 | H66: =Расчет!G1385 -> 90 | I66: 0 | J66: =Расчет!C1365 -> 0.11547005 | K66: =J66 -> 0.11547005 | L66: =Расчет!I1385 -> 0.19052559 | N66: Полоса может быть может не быть
B67: п.А.12.3 Приложения А, ГОСТ 33670-2015 | C67: Скорость транспортного средства | D67: Километры в час, км/ч | E67: Измеритель скорости и длины ИСД-5.1 Зав. № 2024.5379 Инв. № СИ013 | F67: ± 0,15 % | G67: 1 | H67: =Расчет!H1431 -> 20 | I67: 0 | J67: =Расчет!E1409 -> 0.033665016 | K67: =J67 -> 0.033665016 | L67: =Расчет!J1431 -> 0.055547277
B68: п.А.16.7 Приложения А, ГОСТ 33670-2015 | C68: Расстояние между краем бампера и кузовом | D68: Миллиметры, мм | E68: Рулетка RGK R-5 Зав. № 2438 Инв. № СИ035 | F68: ±0,14 мм | G68: 1 | H68: =Расчет!I1480 -> 1 | I68: 0 | J68: =Расчет!E1460 -> 0.080829038 | K68: =J68 -> 0.080829038 | L68: =Расчет!K1480 -> 0.13336791
B69: п.А.16.9 Приложения А, ГОСТ 33670-2015 | C69: Выступание дверной ручки за наружную поверхность кузова | D69: Миллиметры, мм | E69: Линейка измерительная металлическая L300 Зав. № 99 Инв. № СИ023 | F69: ±0,1 мм | G69: 1 | H69: =Расчет!I1519 -> 25 | I69: 0 | J69: =Расчет!E1494 -> 0.057735027 | K69: =J69 -> 0.057735027 | L69: =Расчет!K1519 -> 0.095262794
B70: п.А.16.9 Приложения А, ГОСТ 33670-2015 | C70: Выступание переднего правого повторителя указателя поворота за наружную поверхность кузова | D70: Миллиметры, мм | E70: Линейка измерительная металлическая L300 Зав. № 99 Инв. № СИ023 | F70: ±0,1 мм | G70: 1 | H70: =Расчет!I1520 -> 16 | I70: 0 | J70: =Расчет!E1494 -> 0.057735027 | K70: =J70 -> 0.057735027 | L70: =Расчет!K1520 -> 0.095262794
B71: п.А.21.7 Приложения А, ГОСТ 33670-2015 | C71: Содержание оксида углерода (СО) в отработавших газах ТС с бензиновым двигателем в режиме холостого хода на минимальной частоте вращения коленчатого вала | D71: Процент, % | E71: Газоанализатор многокомпонентный «АВТОТЕСТ-02.02» Зав. № 26403 Инв. № СИ005 | F71: Абсолютная ± 0,03% | G71: 1 | H71: =Расчет!P1570 -> 0 | I71: 0 | J71: =Расчет!E1544 -> 0.017559423 | K71: =J71 -> 0.017559423 | L71: =Расчет!R1570 -> 0.028973048
B72: п.А.21.7 Приложения А, ГОСТ 33670-2015 | C72: Содержание оксида углерода (СО) в отработавших газах ТС с бензиновым двигателем на повышенной частоте вращения коленчатого вала | D72: Процент, % | E72: Газоанализатор многокомпонентный «АВТОТЕСТ-02.02» Зав. № 26403 Инв. № СИ005 | F72: Абсолютная ± 0,03% | G72: 1 | H72: =Расчет!P1571 -> 0 | I72: 0 | J72: =Расчет!E1548 -> 0.017559423 | K72: =J72 -> 0.017559423 | L72: =Расчет!R1571 -> 0.028973048
B73: п.А.21.8 Приложения А, ГОСТ 33670-2015 | C73: Дымность отработавших газов ТС с дизелями в режиме свободного ускорения | D73: натуральный показатель ослабления потока, мˉ¹ | E73: Дымомер АВГ-1Д-4.01 Зав. № 33 Инв. № СИ003 | F73: Абсолютная погрешность ±0,05 мˉ¹ | G73: 1 | H73: =Расчет!F1587 -> #VALUE! | I73: =Расчет!D1594 -> #VALUE! | J73: =Расчет!D1606 -> 0.028868957 | K73: =Расчет!G1610 -> #VALUE! | L73: =Расчет!L1627 -> #VALUE! | N73: Только при диз ТС
B74: п.А.23.1 Приложения А, ГОСТ 33670-2015 | C74: Уровень шума выпуска отработавших газов ТС на холостом ходу при поддержании постоянной целевой частоты вращения | D74: Децибел А, дБА | E74: Шумомер-анализатор спектра портативный ОКТАВА-111 + Микрофонный предусилитель Р200 Зав. № 248268 Инв. № СИ014 | F74: абсолютная ±0,5 дБА | G74: 1 | H74: =Расчет!Q1681 -> 82 | I74: 0 | J74: =Расчет!D1660 -> 0.29011492 | K74: =J74 -> 0.29011492 | L74: =Расчет!S1681 -> 0.47868962
B75: п.А.23.1 Приложения А, ГОСТ 33670-2015 | C75: Уровень шума выпуска отработавших газов ТС в режиме замедления от целевой частоты до минимального частоты холостого хода | D75: Децибел А, дБА | E75: Шумомер-анализатор спектра портативный ОКТАВА-111 + Микрофонный предусилитель Р200 Зав. № 248268 Инв. № СИ014 | F75: абсолютная ±0,5 дБА | G75: 1 | H75: =Расчет!Q1682 -> 80 | I75: 0 | J75: =Расчет!D1660 -> 0.29011492 | K75: =J75 -> 0.29011492 | L75: =Расчет!S1682 -> 0.47868962
B76: п.А.24.3 Приложения А, ГОСТ 33670-2015 | C76: Суммарный люфт в рулевом управлении | D76: Градус, ˚ | E76: Преобразователь измерительный угла поворота ИСЛ-М Зав. № 19694 Инв. № СИ002 | F76: ±0,5 ˚ | G76: 1 | H76: =Расчет!H1728 -> 9 | I76: 0 | J76: =Расчет!D1708 -> 0.29011492 | K76: =J76 -> 0.29011492 | L76: =Расчет!J1728 -> 0.47868962
B77: п 2.2.1, 2.2.5 ГОСТ 22748-77 | C77: Габаритная длина транспортного средства | D77: Миллиметр, мм | E77: Рулетка измерительная металлическая RGK R-5 Зав. № 2438 Инв.№ СИ035 | F77: ±0,3мм | G77: 1 | H77: =Расчет!K1795 -> 4377 | I77: 0 | J77: =Расчет!E1759 -> 0.17320508 | K77: =J77 -> 0.17320508 | L77: =Расчет!M1795 -> 0.71447096
B78: п 2.2.1, 2.2.2.1 ГОСТ 22748-77 | C78: Габаритная ширина транспортного средства | D78: Миллиметр, мм | E78: Рулетка измерительная металлическая RGK R-5 Зав. № 2438 Инв.№ СИ035 | F78: ±0,75мм | G78: 1 | H78: =Расчет!K1796 -> 1700 | I78: 0 | J78: =Расчет!E1763 -> 0.4330127 | K78: =J78 -> 0.4330127 | L78: =Расчет!M1796 -> 0.28578838
B79: п 2.2.1, 2.2.27 ГОСТ 22748-77 | C79: Габаритная высота транспортного средства | D79: Миллиметр, мм | E79: Дальномер лазерный RGK DL50 Зав. № 23F001640 Инв.№ СИ033 | F79: ±2,0мм | G79: 1 | H79: =Расчет!I1834 -> 1470 | I79: 0 | J79: =Расчет!D1813 -> 1.1902381 | K79: =J79 -> 1.1902381 | L79: =Расчет!K1834 -> 1.9638928
B80: Приложение В, ГОСТ 33987-2016 | C80: Длина транспортного средства | D80: Миллиметр, мм | E80: Рулетка измерительная металлическая RGK R-5 Зав. № 2438 Инв.№ СИ035 | F80: ±0,3мм | G80: 1 | H80: =H77 -> 4377 | I80: 0 | J80: =J77 -> 0.17320508 | K80: =K77 -> 0.17320508 | L80: =L77 -> 0.71447096
B81: Приложение В, ГОСТ 33987-2016 | C81: Ширина транспортного средства | D81: Миллиметр, мм | E81: Рулетка измерительная металлическая RGK R-5 Зав. № 2438 Инв.№ СИ035 | F81: ±0,75мм | G81: 1 | H81: =H78 -> 1700 | I81: 0 | J81: =J78 -> 0.4330127 | K81: =K78 -> 0.4330127 | L81: =L78 -> 0.28578838
B82: Приложение В, ГОСТ 33987-2016 | C82: Высота транспортного средства | D82: Миллиметр, мм | E82: Дальномер лазерный RGK DL50 Зав. № 23F001640 Инв.№ СИ033 | F82: ±2,0мм | G82: 1 | H82: =H79 -> 1470 | I82: 0 | J82: =J79 -> 1.1902381 | K82: =K79 -> 1.1902381 | L82: =L79 -> 1.9638928
B83: Приложение Г, ГОСТ 33987-2016 | C83: Масса транспортного средства | D83: Килограмм, кг | E83: Весы автомобильные ИСТОК-30-4П Зав. № 248399 Инв.№ СИ018 | F83: ± 5 кг | G83: 1 | H83: =Расчет!H1881 -> 1240 | I83: 0 | J83: =Расчет!C1863 -> 3.2274861 | K83: =J83 -> 3.2274861 | L83: =Расчет!J1881 -> 5.3253521
B84: Приложение Г, ГОСТ 33987-2016 | C84: Нагрузка на переднюю ось | D84: Килограмм, кг | E84: Весы автомобильные ИСТОК-30-4П Зав. № 248399 Инв.№ СИ018 | F84: ± 5 кг | G84: 1 | H84: =Расчет!H1882 -> 0 | I84: 0 | J84: =J83 -> 3.2274861 | K84: =J84 -> 3.2274861 | L84: =Расчет!J1882 -> 0
B85: Приложение Г, ГОСТ 33987-2016 | C85: Нагрузка на заднюю ось | D85: Килограмм, кг | E85: Весы автомобильные ИСТОК-30-4П Зав. № 248399 Инв.№ СИ018 | F85: ± 5 кг | G85: 1 | H85: =Расчет!H1883 -> 0 | I85: 0 | J85: =J84 -> 3.2274861 | K85: =J85 -> 3.2274861 | L85: =Расчет!J1883 -> 0
B88: Эксперт ИЛ | D88: Евдомахов В.А.
